Workbook

Sheet Ordenes
A1: FECHA DE ENTRADA | B1: ELS | C1: CLIENTE | D1: SUCURSAL | E1: CLIENTE DE CLIENTE | F1: EQUIPO | G1: MARCA | H1: MODELO | I1: N SERIE | J1: AVISO | K1: FECHA DIAGNOSTICO | L1: FECHA ACEPTACION | M1: PRECIO DOLAR | N1: PRECIO PESO | O1: ESTADO FISICO | P1: ESTADO TECNICO | Q1: ESTADO COMERCIAL | R1: VENTA | S1: PAGO | T1: SALDO | U1: MES REP | V1: MES ENTR | W1: SALDO2 | X1: TECNICO | Y1: OC | Z1: REMITO | AA1: FACTURA | AB1: PRESUPUESTO | AC1: AÑO DE REPARACIÓN | AD1: AÑO DE ENTRADA | AE1: AÑO DE ACEP | AF1: MES DE ACEP | AG1: MES FACTURACIÓN | AH1: AÑO FACTURACIÓN
A2: 45302.125 | B2: 988 | C2: Mariel Celio | F2: Programador de Riego | G2: Gadnic | H2: AT 2000 | I2: R70Z5 | K2: 45307.125 | L2: 45307.125 | M2: 21 | N2: 21500 | O2: Enviado | P2: Reparado | Q2: Aceptado | R2: =IF(Q2="Aceptado",N2,0) -> 21500 | S2: 21500 | T2: =IFERROR(+T1+R2-S2,0) -> 0 | U2: =IF(NOT(ISBLANK(K2)),MONTH(K2),"") -> 1 | V2: =IF(NOT(ISBLANK(A2)),MONTH(A2),"") -> 1 | W2: =IFERROR(+S2-R2,0) -> 0 | X2: Diego | Z2: 669 | AA2: 00000-00000000 | AC2: =IF(NOT(ISBLANK(K2)),YEAR(K2),"") -> 2024 | AD2: =IF(NOT(ISBLANK(A2)),YEAR(A2),"") -> 2024 | AE2: =IF(NOT(ISBLANK(L2)),YEAR(L2),"") -> 2024 | AF2: =IF(NOT(ISBLANK(L2)),MONTH(L2),"") -> 1
A3: 45302 | B3: 989 | C3: Mariel Celio | F3: Programador de Riego | G3: Galcon | H3: 9001D-C | I3: GM2529518 | K3: 45307 | L3: 45307 | M3: 49 | N3: 49500 | O3: Enviado | P3: Reparado | Q3: Aceptado | R3: =IF(Q3="Aceptado",N3,0) -> 49500 | S3: 49500 | T3: =IFERROR(+T2+R3-S3,0) -> 0 | U3: =IF(NOT(ISBLANK(K3)),MONTH(K3),"") -> 1 | V3: =IF(NOT(ISBLANK(A3)),MONTH(A3),"") -> 1 | W3: =IFERROR(+S3-R3,0) -> 0 | X3: Diego | Z3: 669 | AC3: =IF(NOT(ISBLANK(K3)),YEAR(K3),"") -> 2024 | AD3: =IF(NOT(ISBLANK(A3)),YEAR(A3),"") -> 2024 | AE3: =IF(NOT(ISBLANK(L3)),YEAR(L3),"") -> 2024 | AF3: =IF(NOT(ISBLANK(L3)),MONTH(L3),"") -> 1
A4: 45302 | B4: 990 | C4: Mariel Celio | F4: Programador de Riego | G4: Galcon | H4: 9001BT | I4: NYMQG | K4: 45307 | L4: 45307 | M4: 49 | N4: 49500 | O4: Enviado | P4: Reparado | Q4: Aceptado | R4: =IF(Q4="Aceptado",N4,0) -> 49500 | S4: 49500 | T4: =IFERROR(+T3+R4-S4,0) -> 0 | U4: =IF(NOT(ISBLANK(K4)),MONTH(K4),"") -> 1 | V4: =IF(NOT(ISBLANK(A4)),MONTH(A4),"") -> 1 | W4: =IFERROR(+S4-R4,0) -> 0 | X4: Diego | Z4: 669 | AC4: =IF(NOT(ISBLANK(K4)),YEAR(K4),"") -> 2024 | AD4: =IF(NOT(ISBLANK(A4)),YEAR(A4),"") -> 2024 | AE4: =IF(NOT(ISBLANK(L4)),YEAR(L4),"") -> 2024 | AF4: =IF(NOT(ISBLANK(L4)),MONTH(L4),"") -> 1
A5: 45314.125 | B5: 991 | C5: Julio Piacentini | F5: Central de arranque y transferencia automática | G5: Datakom | H5: DKG-207 | I5: 2602070172960 | K5: 45303.125 | L5: 45314.125 | M5: 185 | N5: 156500 | O5: Enviado | P5: Reparado | Q5: Aceptado | R5: =IF(Q5="Aceptado",N5,0) -> 156500 | S5: 156500 | T5: =IFERROR(+T4+R5-S5,0) -> 0 | U5: =IF(NOT(ISBLANK(K5)),MONTH(K5),"") -> 1 | V5: =IF(NOT(ISBLANK(A5)),MONTH(A5),"") -> 1 | W5: =IFERROR(+S5-R5,0) -> 0 | X5: Diego | Z5: 673 | AC5: =IF(NOT(ISBLANK(K5)),YEAR(K5),"") -> 2024 | AD5: =IF(NOT(ISBLANK(A5)),YEAR(A5),"") -> 2024 | AE5: =IF(NOT(ISBLANK(L5)),YEAR(L5),"") -> 2024 | AF5: =IF(NOT(ISBLANK(L5)),MONTH(L5),"") -> 1
A6: 45306.125 | B6: 992 | C6: Daniel (Bari Clima) | F6: Placa de caldera | G6: Baxi (Siemens) | H6: Slim ( LMU33.201E149) | I6: 9777 | K6: 45306.125 | L6: 45307.125 | M6: 160 | N6: 140500 | O6: Enviado | P6: Reparado | Q6: Aceptado | R6: =IF(Q6="Aceptado",N6,0) -> 140500 | S6: 140500 | T6: =IFERROR(+T5+R6-S6,0) -> 0 | U6: =IF(NOT(ISBLANK(K6)),MONTH(K6),"") -> 1 | V6: =IF(NOT(ISBLANK(A6)),MONTH(A6),"") -> 1 | W6: =IFERROR(+S6-R6,0) -> 0 | X6: Diego | Z6: 668 | AC6: =IF(NOT(ISBLANK(K6)),YEAR(K6),"") -> 2024 | AD6: =IF(NOT(ISBLANK(A6)),YEAR(A6),"") -> 2024 | AE6: =IF(NOT(ISBLANK(L6)),YEAR(L6),"") -> 2024 | AF6: =IF(NOT(ISBLANK(L6)),MONTH(L6),"") -> 1
A7: 45306 | B7: 993 | C7: Ascensores Lucero | F7: Placa Fuente de ascensor | G7: Automac | H7: A6210 | I7: A7422A | K7: 45307 | L7: 45307 | M7: 45 | N7: 45800 | O7: Enviado | P7: Reparado | Q7: Aceptado | R7: =IF(Q7="Aceptado",N7,0) -> 45800 | S7: 45800 | T7: =IFERROR(+T6+R7-S7,0) -> 0 | U7: =IF(NOT(ISBLANK(K7)),MONTH(K7),"") -> 1 | V7: =IF(NOT(ISBLANK(A7)),MONTH(A7),"") -> 1 | W7: =IFERROR(+S7-R7,0) -> 0 | X7: Diego | Z7: 670 | AA7: 00001-00000292 | AC7: =IF(NOT(ISBLANK(K7)),YEAR(K7),"") -> 2024 | AD7: =IF(NOT(ISBLANK(A7)),YEAR(A7),"") -> 2024 | AE7: =IF(NOT(ISBLANK(L7)),YEAR(L7),"") -> 2024 | AF7: =IF(NOT(ISBLANK(L7)),MONTH(L7),"") -> 1
A8: 45307 | B8: 994 | C8: Daniel (Bari Clima) | F8: Placa de caldera | G8: Caldaia | H8: E312264 (TOP digital Sa26F) | I8: 65E7Q | K8: 45307 | L8: 45311 | M8: 115 | N8: 112500 | O8: Enviado | P8: Reparado | Q8: Aceptado | R8: =IF(Q8="Aceptado",N8,0) -> 112500 | S8: 112500 | T8: =IFERROR(+T7+R8-S8,0) -> 0 | U8: =IF(NOT(ISBLANK(K8)),MONTH(K8),"") -> 1 | V8: =IF(NOT(ISBLANK(A8)),MONTH(A8),"") -> 1 | W8: =IFERROR(+S8-R8,0) -> 0 | X8: Diego | Z8: 672 | AC8: =IF(NOT(ISBLANK(K8)),YEAR(K8),"") -> 2024 | AD8: =IF(NOT(ISBLANK(A8)),YEAR(A8),"") -> 2024 | AE8: =IF(NOT(ISBLANK(L8)),YEAR(L8),"") -> 2024 | AF8: =IF(NOT(ISBLANK(L8)),MONTH(L8),"") -> 1
A9: 45308 | B9: 995 | C9: Privatel | F9: Cargador de baterías( 220vac - 12V/50A) | G9: HT SA | H9: CB-FL-12/750-50-D | I9: JOG9S | K9: 45308 | L9: 45338 | M9: 300 | N9: 256050 | O9: Enviado | P9: Reparado | Q9: Aceptado | R9: =IF(Q9="Aceptado",N9,0) -> 256050 | S9: 256050 | T9: =IFERROR(+T8+R9-S9,0) -> 0 | U9: =IF(NOT(ISBLANK(K9)),MONTH(K9),"") -> 1 | V9: =IF(NOT(ISBLANK(A9)),MONTH(A9),"") -> 1 | W9: =IFERROR(+S9-R9,0) -> 0 | X9: Diego | Z9: 682 | AA9: 00001-00000300 | AC9: =IF(NOT(ISBLANK(K9)),YEAR(K9),"") -> 2024 | AD9: =IF(NOT(ISBLANK(A9)),YEAR(A9),"") -> 2024 | AE9: =IF(NOT(ISBLANK(L9)),YEAR(L9),"") -> 2024 | AF9: =IF(NOT(ISBLANK(L9)),MONTH(L9),"") -> 2
A10: 45314 | B10: 996 | C10: Stec Climatización | F10: Placa de caldera | G10: Caldaia | H10: Genius M30 (11600011) | I10: PV6YG | K10: 45308 | L10: 45324 | M10: 129 | N10: 110000 | O10: Enviado | P10: Reparado | Q10: Aceptado | R10: =IF(Q10="Aceptado",N10,0) -> 110000 | S10: 110000 | T10: =IFERROR(+T9+R10-S10,0) -> 0 | U10: =IF(NOT(ISBLANK(K10)),MONTH(K10),"") -> 1 | V10: =IF(NOT(ISBLANK(A10)),MONTH(A10),"") -> 1 | W10: =IFERROR(+S10-R10,0) -> 0 | X10: Diego | Z10: 671 | AC10: =IF(NOT(ISBLANK(K10)),YEAR(K10),"") -> 2024 | AD10: =IF(NOT(ISBLANK(A10)),YEAR(A10),"") -> 2024 | AE10: =IF(NOT(ISBLANK(L10)),YEAR(L10),"") -> 2024 | AF10: =IF(NOT(ISBLANK(L10)),MONTH(L10),"") -> 2
A11: 45309.125 | B11: 997 | C11: Julio Piacentini | F11: Inverter 48vdc / 220vac - 5000W | G11: Enertik | H11: INVERTER5KW | I11: 92932011101828 | K11: 45309.125 | L11: 46064.125 | M11: 680 | N11: 571880 | O11: BRC | P11: Reparado | Q11: NO Aceptado | R11: =IF(Q11="Aceptado",N11,0) -> 0 | S11: 0 | T11: =IFERROR(+T10+R11-S11,0) -> 0 | U11: =IF(NOT(ISBLANK(K11)),MONTH(K11),"") -> 1 | V11: =IF(NOT(ISBLANK(A11)),MONTH(A11),"") -> 1 | W11: =IFERROR(+S11-R11,0) -> 0 | X11: Diego | AC11: =IF(NOT(ISBLANK(K11)),YEAR(K11),"") -> 2024 | AD11: =IF(NOT(ISBLANK(A11)),YEAR(A11),"") -> 2024 | AE11: =IF(NOT(ISBLANK(L11)),YEAR(L11),"") -> 2026 | AF11: =IF(NOT(ISBLANK(L11)),MONTH(L11),"") -> 2
A12: 45309 | B12: 998 | C12: Julio Piacentini | F12: Central de arranque y transferencia automática | G12: Datakom | H12: DKG-207 | I12: 2602070124518 | K12: 45309 | M12: 171 | N12: 143500 | O12: BRC | P12: Reparado | Q12: A la Espera de Aceptación | R12: =IF(Q12="Aceptado",N12,0) -> 0 | S12: 0 | T12: =IFERROR(+T11+R12-S12,0) -> 0 | U12: =IF(NOT(ISBLANK(K12)),MONTH(K12),"") -> 1 | V12: =IF(NOT(ISBLANK(A12)),MONTH(A12),"") -> 1 | W12: =IFERROR(+S12-R12,0) -> 0 | X12: Diego | AC12: =IF(NOT(ISBLANK(K12)),YEAR(K12),"") -> 2024 | AD12: =IF(NOT(ISBLANK(A12)),YEAR(A12),"") -> 2024 | AE12: =IF(NOT(ISBLANK(L12)),YEAR(L12),"") | AF12: =IF(NOT(ISBLANK(L12)),MONTH(L12),"")
A13: 45310.125 | B13: 999 | C13: ELS | D13: MDP | F13: Micro-Ohmmetro | G13: Megabras | H13: MPK-253 | I13: OA2098J | K13: 45310.125 | L13: 45323.125 | M13: 1100 | N13: 952807 | O13: Enviado | P13: Reparado | Q13: Aceptado | R13: =IF(Q13="Aceptado",N13,0) -> 952807 | S13: 952807 | T13: =IFERROR(+T12+R13-S13,0) -> 0 | U13: =IF(NOT(ISBLANK(K13)),MONTH(K13),"") -> 1 | V13: =IF(NOT(ISBLANK(A13)),MONTH(A13),"") -> 1 | W13: =IFERROR(+S13-R13,0) -> 0 | X13: Diego | AA13: 00001-00000295 | AC13: =IF(NOT(ISBLANK(K13)),YEAR(K13),"") -> 2024 | AD13: =IF(NOT(ISBLANK(A13)),YEAR(A13),"") -> 2024 | AE13: =IF(NOT(ISBLANK(L13)),YEAR(L13),"") -> 2024 | AF13: =IF(NOT(ISBLANK(L13)),MONTH(L13),"") -> 2
A14: 45310 | B14: 1000 | C14: Privatel | F14: Microondas + Grill + Convector | G14: Medion | H14: MD11711 | I14: 0076/08 | K14: 45314 | L14: 45314 | M14: 129 | N14: 108500 | O14: Enviado | P14: Reparado | Q14: Aceptado | R14: =IF(Q14="Aceptado",N14,0) -> 108500 | S14: 108500 | T14: =IFERROR(+T13+R14-S14,0) -> 0 | U14: =IF(NOT(ISBLANK(K14)),MONTH(K14),"") -> 1 | V14: =IF(NOT(ISBLANK(A14)),MONTH(A14),"") -> 1 | W14: =IFERROR(+S14-R14,0) -> 0 | X14: Diego | Z14: 674 | AC14: =IF(NOT(ISBLANK(K14)),YEAR(K14),"") -> 2024 | AD14: =IF(NOT(ISBLANK(A14)),YEAR(A14),"") -> 2024 | AE14: =IF(NOT(ISBLANK(L14)),YEAR(L14),"") -> 2024 | AF14: =IF(NOT(ISBLANK(L14)),MONTH(L14),"") -> 1
A15: 45316 | B15: 1001 | C15: Ascensores Lucero | F15: Variador de velocidad 30 HP | G15: Telemecanique | H15: ATV58HD33N4 | I15: 6W0335000005B | K15: 45317 | L15: 45328 | M15: 1250 | N15: 1052812 | O15: Enviado | P15: No Aceptaron Reparación | Q15: NO Aceptado | R15: =IF(Q15="Aceptado",N15,0) -> 0 | S15: 0 | T15: =IFERROR(+T14+R15-S15,0) -> 0 | U15: =IF(NOT(ISBLANK(K15)),MONTH(K15),"") -> 1 | V15: =IF(NOT(ISBLANK(A15)),MONTH(A15),"") -> 1 | W15: =IFERROR(+S15-R15,0) -> 0 | X15: Diego | AC15: =IF(NOT(ISBLANK(K15)),YEAR(K15),"") -> 2024 | AD15: =IF(NOT(ISBLANK(A15)),YEAR(A15),"") -> 2024 | AE15: =IF(NOT(ISBLANK(L15)),YEAR(L15),"") -> 2024 | AF15: =IF(NOT(ISBLANK(L15)),MONTH(L15),"") -> 2
A16: 45317 | B16: 1002 | C16: Huilque SRL | F16: Horno Convector trifásico 6,25KW | G16: Pauna | H16: Beta 107I | I16: 4580 | K16: 45337 | L16: 45328 | M16: 336 | N16: 285000 | O16: Enviado | P16: Reparado | Q16: Aceptado | R16: =IF(Q16="Aceptado",N16,0) -> 285000 | S16: 285000 | T16: =IFERROR(+T15+R16-S16,0) -> 0 | U16: =IF(NOT(ISBLANK(K16)),MONTH(K16),"") -> 2 | V16: =IF(NOT(ISBLANK(A16)),MONTH(A16),"") -> 1 | W16: =IFERROR(+S16-R16,0) -> 0 | X16: Diego | Z16: 683 | AA16: 00001-00000297 | AC16: =IF(NOT(ISBLANK(K16)),YEAR(K16),"") -> 2024 | AD16: =IF(NOT(ISBLANK(A16)),YEAR(A16),"") -> 2024 | AE16: =IF(NOT(ISBLANK(L16)),YEAR(L16),"") -> 2024 | AF16: =IF(NOT(ISBLANK(L16)),MONTH(L16),"") -> 2
A17: 45316 | B17: 1003 | C17: Ascensores Bariloche | F17: Operador de Puerta | G17: Fermator | H17: VVVF4+ | I17: 11/42739 | K17: 45317 | L17: 45317 | M17: 125 | N17: 105250 | O17: Enviado | P17: Reparado | Q17: Aceptado | R17: =IF(Q17="Aceptado",N17,0) -> 105250 | S17: 105250 | T17: =IFERROR(+T16+R17-S17,0) -> 0 | U17: =IF(NOT(ISBLANK(K17)),MONTH(K17),"") -> 1 | V17: =IF(NOT(ISBLANK(A17)),MONTH(A17),"") -> 1 | W17: =IFERROR(+S17-R17,0) -> 0 | X17: Diego | Z17: 676 | AC17: =IF(NOT(ISBLANK(K17)),YEAR(K17),"") -> 2024 | AD17: =IF(NOT(ISBLANK(A17)),YEAR(A17),"") -> 2024 | AE17: =IF(NOT(ISBLANK(L17)),YEAR(L17),"") -> 2024 | AF17: =IF(NOT(ISBLANK(L17)),MONTH(L17),"") -> 1
A18: 45317 | B18: 1004 | C18: Julio Piacentini | F18: Teclado de música | G18: Casio | H18: CTK-230 | I18: 6369621 | K18: 45322 | L18: 45318 | M18: 100 | N18: 84500 | O18: Enviado | P18: Reparado | Q18: Aceptado | R18: =IF(Q18="Aceptado",N18,0) -> 84500 | S18: 84500 | T18: =IFERROR(+T17+R18-S18,0) -> 0 | U18: =IF(NOT(ISBLANK(K18)),MONTH(K18),"") -> 1 | V18: =IF(NOT(ISBLANK(A18)),MONTH(A18),"") -> 1 | W18: =IFERROR(+S18-R18,0) -> 0 | X18: Diego | Z18: 675 | AC18: =IF(NOT(ISBLANK(K18)),YEAR(K18),"") -> 2024 | AD18: =IF(NOT(ISBLANK(A18)),YEAR(A18),"") -> 2024 | AE18: =IF(NOT(ISBLANK(L18)),YEAR(L18),"") -> 2024 | AF18: =IF(NOT(ISBLANK(L18)),MONTH(L18),"") -> 1
A19: 45321 | B19: 1005 | C19: Andrés Gallardo (X28) | F19: DVR 8CH | G19: HIKVISION | H19: DS-7208HGHI-SHSE | I19: 496010329 | K19: 45323 | L19: 45323 | M19: 67 | N19: 56800 | O19: Enviado | P19: Reparado | Q19: Aceptado | R19: =IF(Q19="Aceptado",N19,0) -> 56800 | S19: 56800 | T19: =IFERROR(+T18+R19-S19,0) -> 0 | U19: =IF(NOT(ISBLANK(K19)),MONTH(K19),"") -> 2 | V19: =IF(NOT(ISBLANK(A19)),MONTH(A19),"") -> 1 | W19: =IFERROR(+S19-R19,0) -> 0 | X19: Diego | Z19: 679 | AC19: =IF(NOT(ISBLANK(K19)),YEAR(K19),"") -> 2024 | AD19: =IF(NOT(ISBLANK(A19)),YEAR(A19),"") -> 2024 | AE19: =IF(NOT(ISBLANK(L19)),YEAR(L19),"") -> 2024 | AF19: =IF(NOT(ISBLANK(L19)),MONTH(L19),"") -> 2
A20: 45323 | B20: 1006 | C20: Daniel (Bari Clima) | F20: Placa de caldera | G20: BaxiRoca | H20: Laura 35/35TH | I20: 42,062,03 | K20: 45323 | L20: 45327 | M20: 175 | N20: 147500 | O20: Enviado | P20: Reparado | Q20: Aceptado | R20: =IF(Q20="Aceptado",N20,0) -> 147500 | S20: 147500 | T20: =IFERROR(+T19+R20-S20,0) -> 0 | U20: =IF(NOT(ISBLANK(K20)),MONTH(K20),"") -> 2 | V20: =IF(NOT(ISBLANK(A20)),MONTH(A20),"") -> 2 | W20: =IFERROR(+S20-R20,0) -> 0 | X20: Diego | Z20: 677 | AC20: =IF(NOT(ISBLANK(K20)),YEAR(K20),"") -> 2024 | AD20: =IF(NOT(ISBLANK(A20)),YEAR(A20),"") -> 2024 | AE20: =IF(NOT(ISBLANK(L20)),YEAR(L20),"") -> 2024 | AF20: =IF(NOT(ISBLANK(L20)),MONTH(L20),"") -> 2
A21: 45323 | B21: 1007 | C21: Daniel (Bari Clima) | F21: Placa de caldera | G21: BaxiRoca | H21: Laura 35/35TH | I21: 42,062,02 | M21: 0 | N21: 0 | O21: BRC | P21: Sin revisar | Q21: A la Espera de Aceptación | R21: =IF(Q21="Aceptado",N21,0) -> 0 | S21: 0 | T21: =IFERROR(+T20+R21-S21,0) -> 0 | U21: =IF(NOT(ISBLANK(K21)),MONTH(K21),"") | V21: =IF(NOT(ISBLANK(A21)),MONTH(A21),"") -> 2 | W21: =IFERROR(+S21-R21,0) -> 0 | X21: Diego | AC21: =IF(NOT(ISBLANK(K21)),YEAR(K21),"") | AD21: =IF(NOT(ISBLANK(A21)),YEAR(A21),"") -> 2024 | AE21: =IF(NOT(ISBLANK(L21)),YEAR(L21),"") | AF21: =IF(NOT(ISBLANK(L21)),MONTH(L21),"")
A22: 45324 | B22: 1008 | C22: Asociación Club Los Pehuenes | F22: Detector de Huella | G22: ZKTECO | H22: K20-ID-SSR-V2 | I22: 3157153200136 | K22: 45338 | L22: 45328 | M22: 197.5 | N22: 167500 | O22: Enviado | P22: Reparado | Q22: Aceptado | R22: =IF(Q22="Aceptado",N22,0) -> 167500 | S22: 167500 | T22: =IFERROR(+T21+R22-S22,0) -> 0 | U22: =IF(NOT(ISBLANK(K22)),MONTH(K22),"") -> 2 | V22: =IF(NOT(ISBLANK(A22)),MONTH(A22),"") -> 2 | W22: =IFERROR(+S22-R22,0) -> 0 | X22: Diego | Z22: 681 | AA22: 00001-00000299 | AC22: =IF(NOT(ISBLANK(K22)),YEAR(K22),"") -> 2024 | AD22: =IF(NOT(ISBLANK(A22)),YEAR(A22),"") -> 2024 | AE22: =IF(NOT(ISBLANK(L22)),YEAR(L22),"") -> 2024 | AF22: =IF(NOT(ISBLANK(L22)),MONTH(L22),"") -> 2
A23: 45329 | B23: 1009 | C23: Distribuidora Patagonia | F23: Notebook | G23: Samsung | H23: NP300E5C | I23: BA68-08754A | J23: 5850 | K23: 45329 | L23: 45329 | M23: 70 | N23: 60000 | O23: Enviado | P23: Reparado | Q23: Aceptado | R23: =IF(Q23="Aceptado",N23,0) -> 60000 | S23: 60000 | T23: =IFERROR(+T22+R23-S23,0) -> 0 | U23: =IF(NOT(ISBLANK(K23)),MONTH(K23),"") -> 2 | V23: =IF(NOT(ISBLANK(A23)),MONTH(A23),"") -> 2 | W23: =IFERROR(+S23-R23,0) -> 0 | X23: Diego | Z23: 678 | AC23: =IF(NOT(ISBLANK(K23)),YEAR(K23),"") -> 2024 | AD23: =IF(NOT(ISBLANK(A23)),YEAR(A23),"") -> 2024 | AE23: =IF(NOT(ISBLANK(L23)),YEAR(L23),"") -> 2024 | AF23: =IF(NOT(ISBLANK(L23)),MONTH(L23),"") -> 2
A24: 45331 | B24: 1010 | C24: Ascensores Lucero | F24: Variador de velocidad 10HP | G24: Telemecanique | H24: ATV31HU75N4 | I24: 8B0931411132 | K24: 45349 | L24: 45334 | M24: 490 | N24: 416500 | O24: Enviado | P24: Reparado | Q24: Aceptado | R24: =IF(Q24="Aceptado",N24,0) -> 416500 | S24: 416500 | T24: =IFERROR(+T23+R24-S24,0) -> 0 | U24: =IF(NOT(ISBLANK(K24)),MONTH(K24),"") -> 2 | V24: =IF(NOT(ISBLANK(A24)),MONTH(A24),"") -> 2 | W24: =IFERROR(+S24-R24,0) -> 0 | X24: Diego | Z24: 688 | AA24: 00001-00000302 | AC24: =IF(NOT(ISBLANK(K24)),YEAR(K24),"") -> 2024 | AD24: =IF(NOT(ISBLANK(A24)),YEAR(A24),"") -> 2024 | AE24: =IF(NOT(ISBLANK(L24)),YEAR(L24),"") -> 2024 | AF24: =IF(NOT(ISBLANK(L24)),MONTH(L24),"") -> 2
A25: 45334 | B25: 1011 | C25: Huilque SRL | F25: Freidora Industrial 8L | G25: Ind. Arg | H25: 8L | I25: IAD5Y | K25: 45335 | L25: 45334 | M25: 90 | N25: 76320 | O25: Enviado | P25: Reparado | Q25: Aceptado | R25: =IF(Q25="Aceptado",N25,0) -> 76320 | S25: 76320 | T25: =IFERROR(+T24+R25-S25,0) -> 0 | U25: =IF(NOT(ISBLANK(K25)),MONTH(K25),"") -> 2 | V25: =IF(NOT(ISBLANK(A25)),MONTH(A25),"") -> 2 | W25: =IFERROR(+S25-R25,0) -> 0 | X25: Diego | Z25: 680 | AA25: 00001-00000296 | AC25: =IF(NOT(ISBLANK(K25)),YEAR(K25),"") -> 2024 | AD25: =IF(NOT(ISBLANK(A25)),YEAR(A25),"") -> 2024 | AE25: =IF(NOT(ISBLANK(L25)),YEAR(L25),"") -> 2024 | AF25: =IF(NOT(ISBLANK(L25)),MONTH(L25),"") -> 2
A26: 45334 | B26: 1012 | C26: Huilque SRL | F26: Freidora Industrial 8L | G26: Ind. Arg. | H26: 8L | I26: E1N6T | K26: 45334 | L26: 45334 | M26: 90 | N26: 76320 | O26: Enviado | P26: Reparado | Q26: Aceptado | R26: =IF(Q26="Aceptado",N26,0) -> 76320 | S26: 76320 | T26: =IFERROR(+T25+R26-S26,0) -> 0 | U26: =IF(NOT(ISBLANK(K26)),MONTH(K26),"") -> 2 | V26: =IF(NOT(ISBLANK(A26)),MONTH(A26),"") -> 2 | W26: =IFERROR(+S26-R26,0) -> 0 | X26: Diego | Z26: 680 | AA26: 00001-00000296 | AC26: =IF(NOT(ISBLANK(K26)),YEAR(K26),"") -> 2024 | AD26: =IF(NOT(ISBLANK(A26)),YEAR(A26),"") -> 2024 | AE26: =IF(NOT(ISBLANK(L26)),YEAR(L26),"") -> 2024 | AF26: =IF(NOT(ISBLANK(L26)),MONTH(L26),"") -> 2
A27: 45335 | B27: 1013 | C27: Distribuidora Patagonia | F27: Impresora | G27: Brother | H27: DCP-T300 | I27: KQSOI | K27: 45335 | L27: 45343 | M27: 135 | N27: 115500 | O27: Enviado | P27: Reparado | Q27: Aceptado | R27: =IF(Q27="Aceptado",N27,0) -> 115500 | S27: 115500 | T27: =IFERROR(+T26+R27-S27,0) -> 0 | U27: =IF(NOT(ISBLANK(K27)),MONTH(K27),"") -> 2 | V27: =IF(NOT(ISBLANK(A27)),MONTH(A27),"") -> 2 | W27: =IFERROR(+S27-R27,0) -> 0 | X27: Diego | Z27: 684 | AA27: 00001-00000303 | AC27: =IF(NOT(ISBLANK(K27)),YEAR(K27),"") -> 2024 | AD27: =IF(NOT(ISBLANK(A27)),YEAR(A27),"") -> 2024 | AE27: =IF(NOT(ISBLANK(L27)),YEAR(L27),"") -> 2024 | AF27: =IF(NOT(ISBLANK(L27)),MONTH(L27),"") -> 2
A28: 45336.125 | B28: 1014 | C28: José (Total Clima) | F28: Sistema de elaboración de cerveza eléctrico | G28: Robobrew | H28: 008695 | I28: 9337310008695 | K28: 45336.125 | L28: 45337.125 | M28: 240 | N28: 240720 | O28: Enviado | P28: Reparado | Q28: Aceptado | R28: =IF(Q28="Aceptado",N28,0) -> 240720 | S28: 240720 | T28: =IFERROR(+T27+R28-S28,0) -> 0 | U28: =IF(NOT(ISBLANK(K28)),MONTH(K28),"") -> 2 | V28: =IF(NOT(ISBLANK(A28)),MONTH(A28),"") -> 2 | W28: =IFERROR(+S28-R28,0) -> 0 | X28: Diego | Z28: 687 | AA28: 00001-00000298 | AC28: =IF(NOT(ISBLANK(K28)),YEAR(K28),"") -> 2024 | AD28: =IF(NOT(ISBLANK(A28)),YEAR(A28),"") -> 2024 | AE28: =IF(NOT(ISBLANK(L28)),YEAR(L28),"") -> 2024 | AF28: =IF(NOT(ISBLANK(L28)),MONTH(L28),"") -> 2
A29: 45343 | B29: 1015 | C29: Hugo | F29: Soldadora inverter 200A | G29: ESAB | H29: LHN 240i Plus | I29: R9KTD | K29: 45345 | L29: 45343 | M29: 280 | N29: 216000 | O29: Enviado | P29: Reparado | Q29: Aceptado | R29: =IF(Q29="Aceptado",N29,0) -> 216000 | S29: 216000 | T29: =IFERROR(+T28+R29-S29,0) -> 0 | U29: =IF(NOT(ISBLANK(K29)),MONTH(K29),"") -> 2 | V29: =IF(NOT(ISBLANK(A29)),MONTH(A29),"") -> 2 | W29: =IFERROR(+S29-R29,0) -> 0 | X29: Diego | Z29: 686 | AC29: =IF(NOT(ISBLANK(K29)),YEAR(K29),"") -> 2024 | AD29: =IF(NOT(ISBLANK(A29)),YEAR(A29),"") -> 2024 | AE29: =IF(NOT(ISBLANK(L29)),YEAR(L29),"") -> 2024 | AF29: =IF(NOT(ISBLANK(L29)),MONTH(L29),"") -> 2
A30: 45343 | B30: 1016 | C30: Jose Luis (Privatel) | F30: TV LCD 32 | G30: Samsung | H30: LN32B530P7R | I30: AZXT3CPS600005W | K30: 45343 | L30: 45343 | M30: 50 | N30: 43000 | O30: Enviado | P30: Reparado | Q30: Aceptado | R30: =IF(Q30="Aceptado",N30,0) -> 43000 | S30: 43000 | T30: =IFERROR(+T29+R30-S30,0) -> 0 | U30: =IF(NOT(ISBLANK(K30)),MONTH(K30),"") -> 2 | V30: =IF(NOT(ISBLANK(A30)),MONTH(A30),"") -> 2 | W30: =IFERROR(+S30-R30,0) -> 0 | X30: Diego | AC30: =IF(NOT(ISBLANK(K30)),YEAR(K30),"") -> 2024 | AD30: =IF(NOT(ISBLANK(A30)),YEAR(A30),"") -> 2024 | AE30: =IF(NOT(ISBLANK(L30)),YEAR(L30),"") -> 2024 | AF30: =IF(NOT(ISBLANK(L30)),MONTH(L30),"") -> 2
A31: 45344 | B31: 1017 | C31: Ariel Lotito | F31: Placa de caldera | G31: Ariston | H31: AMPC-GAL1 MCU STD MED FF | I31: 1709066A0178 | K31: 45344 | L31: 45345 | M31: 140 | N31: 110000 | O31: Enviado | P31: Reparado | Q31: Aceptado | R31: =IF(Q31="Aceptado",N31,0) -> 110000 | S31: 110000 | T31: =IFERROR(+T30+R31-S31,0) -> 0 | U31: =IF(NOT(ISBLANK(K31)),MONTH(K31),"") -> 2 | V31: =IF(NOT(ISBLANK(A31)),MONTH(A31),"") -> 2 | W31: =IFERROR(+S31-R31,0) -> 0 | X31: Diego | Z31: 685 | AC31: =IF(NOT(ISBLANK(K31)),YEAR(K31),"") -> 2024 | AD31: =IF(NOT(ISBLANK(A31)),YEAR(A31),"") -> 2024 | AE31: =IF(NOT(ISBLANK(L31)),YEAR(L31),"") -> 2024 | AF31: =IF(NOT(ISBLANK(L31)),MONTH(L31),"") -> 2
A32: 45344 | B32: 1018 | C32: Distribuidora Patagonia | F32: Impresora Laser | G32: Brother | H32: HL-1212W | I32: U63982F8N692142 | J32: 5942 | K32: 45350 | L32: 45349 | M32: 84 | N32: 72500 | O32: Enviado | P32: Reparado | Q32: Aceptado | R32: =IF(Q32="Aceptado",N32,0) -> 72500 | S32: 72500 | T32: =IFERROR(+T31+R32-S32,0) -> 0 | U32: =IF(NOT(ISBLANK(K32)),MONTH(K32),"") -> 2 | V32: =IF(NOT(ISBLANK(A32)),MONTH(A32),"") -> 2 | W32: =IFERROR(+S32-R32,0) -> 0 | X32: Diego | Z32: 690 | AC32: =IF(NOT(ISBLANK(K32)),YEAR(K32),"") -> 2024 | AD32: =IF(NOT(ISBLANK(A32)),YEAR(A32),"") -> 2024 | AE32: =IF(NOT(ISBLANK(L32)),YEAR(L32),"") -> 2024 | AF32: =IF(NOT(ISBLANK(L32)),MONTH(L32),"") -> 2
A33: 45348 | B33: 1019 | C33: Alma Del Lago (Almasur S.A.) | F33: Placa de ascensor | G33: Automac | H33: A6220v4 | I33: 199221020 | K33: 45348 | L33: 45349 | M33: 120 | N33: 103000 | O33: Enviado | P33: Reparado | Q33: Aceptado | R33: =IF(Q33="Aceptado",N33,0) -> 103000 | S33: 103000 | T33: =IFERROR(+T32+R33-S33,0) -> 0 | U33: =IF(NOT(ISBLANK(K33)),MONTH(K33),"") -> 2 | V33: =IF(NOT(ISBLANK(A33)),MONTH(A33),"") -> 2 | W33: =IFERROR(+S33-R33,0) -> 0 | X33: Diego | Z33: 689 | AA33: 00001-00000301 | AC33: =IF(NOT(ISBLANK(K33)),YEAR(K33),"") -> 2024 | AD33: =IF(NOT(ISBLANK(A33)),YEAR(A33),"") -> 2024 | AE33: =IF(NOT(ISBLANK(L33)),YEAR(L33),"") -> 2024 | AF33: =IF(NOT(ISBLANK(L33)),MONTH(L33),"") -> 2
A34: 45350.125 | B34: 1020 | C34: Leandro Slosel | F34: Sistema de control de Jacuzzi | G34: Balboa | H34: GL2001M3 | I34: 55216-031106160001 | K34: 45352.125 | L34: 45352.125 | M34: 385 | N34: 331100 | O34: Enviado | P34: Reparado | Q34: Aceptado | R34: =IF(Q34="Aceptado",N34,0) -> 331100 | S34: 331100 | T34: =IFERROR(+T33+R34-S34,0) -> 0 | U34: =IF(NOT(ISBLANK(K34)),MONTH(K34),"") -> 3 | V34: =IF(NOT(ISBLANK(A34)),MONTH(A34),"") -> 2 | W34: =IFERROR(+S34-R34,0) -> 0 | X34: Diego | Z34: 691 | AA34: 00001-00000304 | AC34: =IF(NOT(ISBLANK(K34)),YEAR(K34),"") -> 2024 | AD34: =IF(NOT(ISBLANK(A34)),YEAR(A34),"") -> 2024 | AE34: =IF(NOT(ISBLANK(L34)),YEAR(L34),"") -> 2024 | AF34: =IF(NOT(ISBLANK(L34)),MONTH(L34),"") -> 3
A35: 45352.125 | B35: 1021 | C35: Julio Piacentini | F35: Inverter 12vdc / 220vac - 600W | G35: Enertik | H35: IE-600-12 | I35: E05Q026 | K35: 45352.125 | M35: 110 | N35: 104000 | O35: BRC | P35: Reparado | Q35: A la Espera de Aceptación | R35: =IF(Q35="Aceptado",N35,0) -> 0 | S35: 0 | T35: =IFERROR(+T34+R35-S35,0) -> 0 | U35: =IF(NOT(ISBLANK(K35)),MONTH(K35),"") -> 3 | V35: =IF(NOT(ISBLANK(A35)),MONTH(A35),"") -> 3 | W35: =IFERROR(+S35-R35,0) -> 0 | X35: Diego | AC35: =IF(NOT(ISBLANK(K35)),YEAR(K35),"") -> 2024 | AD35: =IF(NOT(ISBLANK(A35)),YEAR(A35),"") -> 2024 | AE35: =IF(NOT(ISBLANK(L35)),YEAR(L35),"") | AF35: =IF(NOT(ISBLANK(L35)),MONTH(L35),"")
A36: 45357 | B36: 1022 | C36: Julio Piacentini | F36: Cargador de baterías | G36: Makita | H36: DC18RA | I36: V3C1L | K36: 45357 | L36: 45357 | M36: 52 | N36: 45000 | O36: Enviado | P36: Reparado | Q36: Aceptado | R36: =IF(Q36="Aceptado",N36,0) -> 45000 | S36: 45000 | T36: =IFERROR(+T35+R36-S36,0) -> 0 | U36: =IF(NOT(ISBLANK(K36)),MONTH(K36),"") -> 3 | V36: =IF(NOT(ISBLANK(A36)),MONTH(A36),"") -> 3 | W36: =IFERROR(+S36-R36,0) -> 0 | X36: Diego | Z36: 692 | AC36: =IF(NOT(ISBLANK(K36)),YEAR(K36),"") -> 2024 | AD36: =IF(NOT(ISBLANK(A36)),YEAR(A36),"") -> 2024 | AE36: =IF(NOT(ISBLANK(L36)),YEAR(L36),"") -> 2024 | AF36: =IF(NOT(ISBLANK(L36)),MONTH(L36),"") -> 3
A37: 45357 | B37: 1023 | C37: Mamuschka SRL | F37: Placa de unidad exterior multisplit | G37: Mitsubishi | H37: INV20Y-BOARD KE76B5INV20Y-BOARD KE76B564G0264G02 | I37: 160112B | K37: 45357 | L37: 45364 | M37: 50 | N37: 49500 | O37: Enviado | P37: Reparado | Q37: Aceptado | R37: =IF(Q37="Aceptado",N37,0) -> 49500 | S37: 49500 | T37: =IFERROR(+T36+R37-S37,0) -> 0 | U37: =IF(NOT(ISBLANK(K37)),MONTH(K37),"") -> 3 | V37: =IF(NOT(ISBLANK(A37)),MONTH(A37),"") -> 3 | W37: =IFERROR(+S37-R37,0) -> 0 | X37: Diego | Z37: 693 | AA37: 00001-00000305 | AC37: =IF(NOT(ISBLANK(K37)),YEAR(K37),"") -> 2024 | AD37: =IF(NOT(ISBLANK(A37)),YEAR(A37),"") -> 2024 | AE37: =IF(NOT(ISBLANK(L37)),YEAR(L37),"") -> 2024 | AF37: =IF(NOT(ISBLANK(L37)),MONTH(L37),"") -> 3
A38: 45362.125 | B38: 1024 | C38: Abuelo Ian | F38: Motor de portón eléctrico | G38: Central Tem | H38: PCI 0106/2 | I38: K371U | K38: 45362.125 | L38: 45362.125 | M38: 63 | N38: 55000 | O38: Enviado | P38: Reparado | Q38: Aceptado | R38: =IF(Q38="Aceptado",N38,0) -> 55000 | S38: 55000 | T38: =IFERROR(+T37+R38-S38,0) -> 0 | U38: =IF(NOT(ISBLANK(K38)),MONTH(K38),"") -> 3 | V38: =IF(NOT(ISBLANK(A38)),MONTH(A38),"") -> 3 | W38: =IFERROR(+S38-R38,0) -> 0 | X38: Diego | AC38: =IF(NOT(ISBLANK(K38)),YEAR(K38),"") -> 2024 | AD38: =IF(NOT(ISBLANK(A38)),YEAR(A38),"") -> 2024 | AE38: =IF(NOT(ISBLANK(L38)),YEAR(L38),"") -> 2024 | AF38: =IF(NOT(ISBLANK(L38)),MONTH(L38),"") -> 3
A39: 45363.125 | B39: 1025 | C39: Nicolás (Placas Lav_Sec ropas) | F39: Placa de Lavarropas Next Eco | G39: Drean | H39: 772204100 | I39: 3009162 | K39: 45363.125 | L39: 45366.125 | M39: 61 | N39: 53000 | O39: Enviado | P39: Reparado | Q39: Aceptado | R39: =IF(Q39="Aceptado",N39,0) -> 53000 | S39: 53000 | T39: =IFERROR(+T38+R39-S39,0) -> 0 | U39: =IF(NOT(ISBLANK(K39)),MONTH(K39),"") -> 3 | V39: =IF(NOT(ISBLANK(A39)),MONTH(A39),"") -> 3 | W39: =IFERROR(+S39-R39,0) -> 0 | X39: Diego | Z39: 694 | AC39: =IF(NOT(ISBLANK(K39)),YEAR(K39),"") -> 2024 | AD39: =IF(NOT(ISBLANK(A39)),YEAR(A39),"") -> 2024 | AE39: =IF(NOT(ISBLANK(L39)),YEAR(L39),"") -> 2024 | AF39: =IF(NOT(ISBLANK(L39)),MONTH(L39),"") -> 3
A40: 45363.125 | B40: 1026 | C40: Nicolás (Placas Lav_Sec ropas) | F40: Placa de Secarropas ASL70C | G40: Ariston | H40: LT C126 | I40: 0639 | K40: 45363.125 | L40: 45366.125 | M40: 127 | N40: 110000 | O40: Enviado | P40: Reparado | Q40: Aceptado | R40: =IF(Q40="Aceptado",N40,0) -> 110000 | S40: 110000 | T40: =IFERROR(+T39+R40-S40,0) -> 0 | U40: =IF(NOT(ISBLANK(K40)),MONTH(K40),"") -> 3 | V40: =IF(NOT(ISBLANK(A40)),MONTH(A40),"") -> 3 | W40: =IFERROR(+S40-R40,0) -> 0 | X40: Diego | Z40: 694 | AC40: =IF(NOT(ISBLANK(K40)),YEAR(K40),"") -> 2024 | AD40: =IF(NOT(ISBLANK(A40)),YEAR(A40),"") -> 2024 | AE40: =IF(NOT(ISBLANK(L40)),YEAR(L40),"") -> 2024 | AF40: =IF(NOT(ISBLANK(L40)),MONTH(L40),"") -> 3
A41: 45363 | B41: 1027 | C41: Nicolás (Placas Lav_Sec ropas) | F41: Baby monitor | G41: Philips | H41: scd501 | I41: GC2TK | K41: 45369 | L41: 45366 | M41: 30 | N41: 26000 | O41: Enviado | P41: Reparado | Q41: Aceptado | R41: =IF(Q41="Aceptado",N41,0) -> 26000 | S41: 26000 | T41: =IFERROR(+T40+R41-S41,0) -> 0 | U41: =IF(NOT(ISBLANK(K41)),MONTH(K41),"") -> 3 | V41: =IF(NOT(ISBLANK(A41)),MONTH(A41),"") -> 3 | W41: =IFERROR(+S41-R41,0) -> 0 | X41: Diego | Z41: 694 | AC41: =IF(NOT(ISBLANK(K41)),YEAR(K41),"") -> 2024 | AD41: =IF(NOT(ISBLANK(A41)),YEAR(A41),"") -> 2024 | AE41: =IF(NOT(ISBLANK(L41)),YEAR(L41),"") -> 2024 | AF41: =IF(NOT(ISBLANK(L41)),MONTH(L41),"") -> 3
A42: 45364 | B42: 1028 | C42: Distribuidora Patagonia | F42: Multifuncion Laser | G42: Sharp | H42: AL-2020 | I42: 85051196 | K42: 45390 | L42: 45456 | M42: 172 | N42: 172000 | O42: Enviado | P42: Reparado | Q42: Aceptado | R42: =IF(Q42="Aceptado",N42,0) -> 172000 | S42: 172000 | T42: =IFERROR(+T41+R42-S42,0) -> 0 | U42: =IF(NOT(ISBLANK(K42)),MONTH(K42),"") -> 4 | V42: =IF(NOT(ISBLANK(A42)),MONTH(A42),"") -> 3 | W42: =IFERROR(+S42-R42,0) -> 0 | X42: Diego | Z42: 697 | AA42: 00001-00000030 | AC42: =IF(NOT(ISBLANK(K42)),YEAR(K42),"") -> 2024 | AD42: =IF(NOT(ISBLANK(A42)),YEAR(A42),"") -> 2024 | AE42: =IF(NOT(ISBLANK(L42)),YEAR(L42),"") -> 2024 | AF42: =IF(NOT(ISBLANK(L42)),MONTH(L42),"") -> 6
A43: 45366 | B43: 1029 | C43: QUASAR INFORMATICA SA | F43: Cargador Automático Inteligente 12V 15A | G43: Enertik | H43: IC-15-12 | I43: 1L129 | K43: 45366 | L43: 45366 | M43: 226 | N43: 195500 | O43: BRC | P43: Reparado | Q43: Aceptado | R43: =IF(Q43="Aceptado",N43,0) -> 195500 | S43: 195500 | T43: =IFERROR(+T42+R43-S43,0) -> 0 | U43: =IF(NOT(ISBLANK(K43)),MONTH(K43),"") -> 3 | V43: =IF(NOT(ISBLANK(A43)),MONTH(A43),"") -> 3 | W43: =IFERROR(+S43-R43,0) -> 0 | X43: Diego | Z43: 695 | AC43: =IF(NOT(ISBLANK(K43)),YEAR(K43),"") -> 2024 | AD43: =IF(NOT(ISBLANK(A43)),YEAR(A43),"") -> 2024 | AE43: =IF(NOT(ISBLANK(L43)),YEAR(L43),"") -> 2024 | AF43: =IF(NOT(ISBLANK(L43)),MONTH(L43),"") -> 3
A44: 45366 | B44: 1030 | C44: ELS | D44: MDP | F44: Cargador de Baterias 220VAC - 48V/20A | G44: Melex | H44: M4820 | I44: 3052 | K44: 45368 | L44: 45368 | M44: 0 | N44: 28635 | O44: Enviado | P44: Reparado | Q44: Aceptado | R44: =IF(Q44="Aceptado",N44,0) -> 28635 | S44: 28635 | T44: =IFERROR(+T43+R44-S44,0) -> 0 | U44: =IF(NOT(ISBLANK(K44)),MONTH(K44),"") -> 3 | V44: =IF(NOT(ISBLANK(A44)),MONTH(A44),"") -> 3 | W44: =IFERROR(+S44-R44,0) -> 0 | X44: Diego | AC44: =IF(NOT(ISBLANK(K44)),YEAR(K44),"") -> 2024 | AD44: =IF(NOT(ISBLANK(A44)),YEAR(A44),"") -> 2024 | AE44: =IF(NOT(ISBLANK(L44)),YEAR(L44),"") -> 2024 | AF44: =IF(NOT(ISBLANK(L44)),MONTH(L44),"") -> 3
A45: 45377 | B45: 1031 | C45: Julio Piacentini | F45: Smart TV 65" | G45: Philips | H45: 65PUD6794/77 | I45: ZA1A2040005413 | K45: 45380 | L45: 45381 | M45: 0 | N45: 195500 | O45: BRC | P45: No Aceptaron Reparación | Q45: NO Aceptado | R45: =IF(Q45="Aceptado",N45,0) -> 0 | S45: 0 | T45: =IFERROR(+T44+R45-S45,0) -> 0 | U45: =IF(NOT(ISBLANK(K45)),MONTH(K45),"") -> 3 | V45: =IF(NOT(ISBLANK(A45)),MONTH(A45),"") -> 3 | W45: =IFERROR(+S45-R45,0) -> 0 | X45: Diego | AC45: =IF(NOT(ISBLANK(K45)),YEAR(K45),"") -> 2024 | AD45: =IF(NOT(ISBLANK(A45)),YEAR(A45),"") -> 2024 | AE45: =IF(NOT(ISBLANK(L45)),YEAR(L45),"") -> 2024 | AF45: =IF(NOT(ISBLANK(L45)),MONTH(L45),"") -> 3
A46: 45378 | B46: 1032 | C46: Alma Del Lago (Almasur S.A.) | F46: Placa de ascensor | G46: Automac | H46: A6220v4 | I46: 199221020 | K46: 45378 | L46: 45379 | M46: 131 | N46: 115000 | O46: Enviado | P46: Reparado | Q46: Aceptado | R46: =IF(Q46="Aceptado",N46,0) -> 115000 | S46: 115000 | T46: =IFERROR(+T45+R46-S46,0) -> 0 | U46: =IF(NOT(ISBLANK(K46)),MONTH(K46),"") -> 3 | V46: =IF(NOT(ISBLANK(A46)),MONTH(A46),"") -> 3 | W46: =IFERROR(+S46-R46,0) -> 0 | X46: Diego | Z46: 696 | AC46: =IF(NOT(ISBLANK(K46)),YEAR(K46),"") -> 2024 | AD46: =IF(NOT(ISBLANK(A46)),YEAR(A46),"") -> 2024 | AE46: =IF(NOT(ISBLANK(L46)),YEAR(L46),"") -> 2024 | AF46: =IF(NOT(ISBLANK(L46)),MONTH(L46),"") -> 3
A47: 45378 | B47: 1033 | C47: Rolando Soldadora MIG-MAG | F47: Cargador de Batería 12v 20A | G47: Enertik | H47: EC-20-12 | I47: EC2012S063 | K47: 45378 | L47: 45379 | M47: 90 | N47: 79500 | O47: Enviado | P47: Reparado | Q47: Aceptado | R47: =IF(Q47="Aceptado",N47,0) -> 79500 | S47: 79500 | T47: =IFERROR(+T46+R47-S47,0) -> 0 | U47: =IF(NOT(ISBLANK(K47)),MONTH(K47),"") -> 3 | V47: =IF(NOT(ISBLANK(A47)),MONTH(A47),"") -> 3 | W47: =IFERROR(+S47-R47,0) -> 0 | X47: Diego | AC47: =IF(NOT(ISBLANK(K47)),YEAR(K47),"") -> 2024 | AD47: =IF(NOT(ISBLANK(A47)),YEAR(A47),"") -> 2024 | AE47: =IF(NOT(ISBLANK(L47)),YEAR(L47),"") -> 2024 | AF47: =IF(NOT(ISBLANK(L47)),MONTH(L47),"") -> 3
A48: 45379 | B48: 1034 | C48: Mamuschka SRL | F48: Variador de velocidad 7A | G48: Weg | H48: CFW500A07P0S2N | I48: 7909018028743 | K48: 45379 | L48: 45380 | M48: 250 | N48: 219000 | O48: Enviado | P48: Reparado | Q48: Aceptado | R48: =IF(Q48="Aceptado",N48,0) -> 219000 | S48: 219000 | T48: =IFERROR(+T47+R48-S48,0) -> 0 | U48: =IF(NOT(ISBLANK(K48)),MONTH(K48),"") -> 3 | V48: =IF(NOT(ISBLANK(A48)),MONTH(A48),"") -> 3 | W48: =IFERROR(+S48-R48,0) -> 0 | X48: Diego | Z48: 699 | AA48: 00001-00000306 | AC48: =IF(NOT(ISBLANK(K48)),YEAR(K48),"") -> 2024 | AD48: =IF(NOT(ISBLANK(A48)),YEAR(A48),"") -> 2024 | AE48: =IF(NOT(ISBLANK(L48)),YEAR(L48),"") -> 2024 | AF48: =IF(NOT(ISBLANK(L48)),MONTH(L48),"") -> 3
A49: 45379 | B49: 1035 | C49: Aguirre (Inversor Enertik) | F49: Invereter 5KW | G49: Enertik | H49: ICB-5K-48 | I49: 92931911100882 | K49: 45379 | L49: 45385 | M49: 450 | N49: 394200 | O49: Enviado | P49: Reparado | Q49: Aceptado | R49: =IF(Q49="Aceptado",N49,0) -> 394200 | S49: 394200 | T49: =IFERROR(+T48+R49-S49,0) -> 0 | U49: =IF(NOT(ISBLANK(K49)),MONTH(K49),"") -> 3 | V49: =IF(NOT(ISBLANK(A49)),MONTH(A49),"") -> 3 | W49: =IFERROR(+S49-R49,0) -> 0 | X49: Diego | Z49: 698 | AC49: =IF(NOT(ISBLANK(K49)),YEAR(K49),"") -> 2024 | AD49: =IF(NOT(ISBLANK(A49)),YEAR(A49),"") -> 2024 | AE49: =IF(NOT(ISBLANK(L49)),YEAR(L49),"") -> 2024 | AF49: =IF(NOT(ISBLANK(L49)),MONTH(L49),"") -> 4
A50: 45392 | B50: 1036 | C50: Stec Climatización | F50: Placa de caldera | G50: Ariston | H50: BT2M-HS MI/FFI MICRO (Microtec) | I50: 2406032V2177 | K50: 45392 | L50: 45393 | M50: 152 | N50: 135000 | O50: Enviado | P50: Reparado | Q50: Aceptado | R50: =IF(Q50="Aceptado",N50,0) -> 135000 | S50: 135000 | T50: =IFERROR(+T49+R50-S50,0) -> 0 | U50: =IF(NOT(ISBLANK(K50)),MONTH(K50),"") -> 4 | V50: =IF(NOT(ISBLANK(A50)),MONTH(A50),"") -> 4 | W50: =IFERROR(+S50-R50,0) -> 0 | X50: Diego | Z50: 700 | AC50: =IF(NOT(ISBLANK(K50)),YEAR(K50),"") -> 2024 | AD50: =IF(NOT(ISBLANK(A50)),YEAR(A50),"") -> 2024 | AE50: =IF(NOT(ISBLANK(L50)),YEAR(L50),"") -> 2024 | AF50: =IF(NOT(ISBLANK(L50)),MONTH(L50),"") -> 4
A51: 45392 | B51: 1037 | C51: Daniel Calderísta | F51: Placa de caldera | G51: Caldaia | H51: E321060 (TOP a perilla) | I51: DZSNF | K51: 45393 | L51: 45393 | M51: 122 | N51: 108000 | O51: Enviado | P51: Reparado | Q51: Aceptado | R51: =IF(Q51="Aceptado",N51,0) -> 108000 | S51: 108000 | T51: =IFERROR(+T50+R51-S51,0) -> 0 | U51: =IF(NOT(ISBLANK(K51)),MONTH(K51),"") -> 4 | V51: =IF(NOT(ISBLANK(A51)),MONTH(A51),"") -> 4 | W51: =IFERROR(+S51-R51,0) -> 0 | X51: Diego | Z51: 702 | AC51: =IF(NOT(ISBLANK(K51)),YEAR(K51),"") -> 2024 | AD51: =IF(NOT(ISBLANK(A51)),YEAR(A51),"") -> 2024 | AE51: =IF(NOT(ISBLANK(L51)),YEAR(L51),"") -> 2024 | AF51: =IF(NOT(ISBLANK(L51)),MONTH(L51),"") -> 4
A52: 45393 | B52: 1038 | C52: Daniel Calderísta | F52: Placa de caldera de condensación | G52: Ariston | H52: GAL-EVO2 SE ENTRY ( MATIS ) | I52: LM2021220435 | K52: 45393 | L52: 45393 | M52: 147 | N52: 130000 | O52: Enviado | P52: Reparado | Q52: Aceptado | R52: =IF(Q52="Aceptado",N52,0) -> 130000 | S52: 130000 | T52: =IFERROR(+T51+R52-S52,0) -> 0 | U52: =IF(NOT(ISBLANK(K52)),MONTH(K52),"") -> 4 | V52: =IF(NOT(ISBLANK(A52)),MONTH(A52),"") -> 4 | W52: =IFERROR(+S52-R52,0) -> 0 | X52: Diego | Z52: 701 | AC52: =IF(NOT(ISBLANK(K52)),YEAR(K52),"") -> 2024 | AD52: =IF(NOT(ISBLANK(A52)),YEAR(A52),"") -> 2024 | AE52: =IF(NOT(ISBLANK(L52)),YEAR(L52),"") -> 2024 | AF52: =IF(NOT(ISBLANK(L52)),MONTH(L52),"") -> 4
A53: 45399 | B53: 1039 | C53: Jonathan Chacón | F53: Placa de caldera | G53: Ariston | H53: BS II (GAL2-UNI LOW-TIER FF CN) | I53: 301116GI2552 | K53: 45400 | L53: 45404 | M53: 168 | N53: 149000 | O53: Enviado | P53: Reparado | Q53: Aceptado | R53: =IF(Q53="Aceptado",N53,0) -> 149000 | S53: 149000 | T53: =IFERROR(+T52+R53-S53,0) -> 0 | U53: =IF(NOT(ISBLANK(K53)),MONTH(K53),"") -> 4 | V53: =IF(NOT(ISBLANK(A53)),MONTH(A53),"") -> 4 | W53: =IFERROR(+S53-R53,0) -> 0 | X53: Diego | Z53: 704 | AA53: 00001-00000027 | AC53: =IF(NOT(ISBLANK(K53)),YEAR(K53),"") -> 2024 | AD53: =IF(NOT(ISBLANK(A53)),YEAR(A53),"") -> 2024 | AE53: =IF(NOT(ISBLANK(L53)),YEAR(L53),"") -> 2024 | AF53: =IF(NOT(ISBLANK(L53)),MONTH(L53),"") -> 4
A54: 45399 | B54: 1040 | C54: Daniel Calderísta | F54: Placa de caldera | G54: Caldaia | H54: E321060 (TOP a perilla) | I54: H1U6J | K54: 45399 | L54: 45428 | M54: 140 | N54: 112500 | O54: Enviado | P54: Reparado | Q54: Aceptado | R54: =IF(Q54="Aceptado",N54,0) -> 112500 | S54: 112500 | T54: =IFERROR(+T53+R54-S54,0) -> 0 | U54: =IF(NOT(ISBLANK(K54)),MONTH(K54),"") -> 4 | V54: =IF(NOT(ISBLANK(A54)),MONTH(A54),"") -> 4 | W54: =IFERROR(+S54-R54,0) -> 0 | X54: Diego | Z54: 714 | AC54: =IF(NOT(ISBLANK(K54)),YEAR(K54),"") -> 2024 | AD54: =IF(NOT(ISBLANK(A54)),YEAR(A54),"") -> 2024 | AE54: =IF(NOT(ISBLANK(L54)),YEAR(L54),"") -> 2024 | AF54: =IF(NOT(ISBLANK(L54)),MONTH(L54),"") -> 5
A55: 45404 | B55: 1041 | C55: Gerardo (Caldera Pina) | F55: Placa de caldera | G55: Baxi | H55: Mainfour 24 (CS0261F) | I55: 00870 | K55: 45404 | L55: 45404 | M55: 179 | N55: 160000 | O55: Enviado | P55: Reparado | Q55: Aceptado | R55: =IF(Q55="Aceptado",N55,0) -> 160000 | S55: 160000 | T55: =IFERROR(+T54+R55-S55,0) -> 0 | U55: =IF(NOT(ISBLANK(K55)),MONTH(K55),"") -> 4 | V55: =IF(NOT(ISBLANK(A55)),MONTH(A55),"") -> 4 | W55: =IFERROR(+S55-R55,0) -> 0 | X55: Diego | Z55: 703 | AC55: =IF(NOT(ISBLANK(K55)),YEAR(K55),"") -> 2024 | AD55: =IF(NOT(ISBLANK(A55)),YEAR(A55),"") -> 2024 | AE55: =IF(NOT(ISBLANK(L55)),YEAR(L55),"") -> 2024 | AF55: =IF(NOT(ISBLANK(L55)),MONTH(L55),"") -> 4
A56: 45405 | B56: 1042 | C56: Distribuidora Patagonia | F56: Placa main de impresora | G56: HP | H56: CF427-60001 | I56: YJ120KG | K56: 45405 | L56: 45405 | M56: 27 | N56: 25000 | O56: Enviado | P56: Reparado | Q56: Aceptado | R56: =IF(Q56="Aceptado",N56,0) -> 25000 | S56: 25000 | T56: =IFERROR(+T55+R56-S56,0) -> 0 | U56: =IF(NOT(ISBLANK(K56)),MONTH(K56),"") -> 4 | V56: =IF(NOT(ISBLANK(A56)),MONTH(A56),"") -> 4 | W56: =IFERROR(+S56-R56,0) -> 0 | X56: Diego | Z56: 705 | AC56: =IF(NOT(ISBLANK(K56)),YEAR(K56),"") -> 2024 | AD56: =IF(NOT(ISBLANK(A56)),YEAR(A56),"") -> 2024 | AE56: =IF(NOT(ISBLANK(L56)),YEAR(L56),"") -> 2024 | AF56: =IF(NOT(ISBLANK(L56)),MONTH(L56),"") -> 4
A57: 45406 | B57: 1043 | C57: Gerardo (Caldera Pina) | F57: Placa de caldera | G57: Baxi | H57: MainFour 24 (CS0263C) | I57: 5101141009 | K57: 45406 | L57: 45406 | M57: 180 | N57: 160000 | O57: Enviado | P57: Reparado | Q57: Aceptado | R57: =IF(Q57="Aceptado",N57,0) -> 160000 | S57: 160000 | T57: =IFERROR(+T56+R57-S57,0) -> 0 | U57: =IF(NOT(ISBLANK(K57)),MONTH(K57),"") -> 4 | V57: =IF(NOT(ISBLANK(A57)),MONTH(A57),"") -> 4 | W57: =IFERROR(+S57-R57,0) -> 0 | X57: Diego | Z57: 706 | AC57: =IF(NOT(ISBLANK(K57)),YEAR(K57),"") -> 2024 | AD57: =IF(NOT(ISBLANK(A57)),YEAR(A57),"") -> 2024 | AE57: =IF(NOT(ISBLANK(L57)),YEAR(L57),"") -> 2024 | AF57: =IF(NOT(ISBLANK(L57)),MONTH(L57),"") -> 4
A58: 45407 | B58: 1044 | C58: Daniel (Bari Clima) | F58: Placa de caldera | G58: Baxi | H58: eco 240 Fi (ECO 240 Fi) | I58: 56.5389.1 | K58: 45407 | M58: 190 | N58: 165000 | O58: BRC | P58: En Reparación | Q58: A la Espera de Aceptación | R58: =IF(Q58="Aceptado",N58,0) -> 0 | S58: 0 | T58: =IFERROR(+T57+R58-S58,0) -> 0 | U58: =IF(NOT(ISBLANK(K58)),MONTH(K58),"") -> 4 | V58: =IF(NOT(ISBLANK(A58)),MONTH(A58),"") -> 4 | W58: =IFERROR(+S58-R58,0) -> 0 | X58: Diego | AC58: =IF(NOT(ISBLANK(K58)),YEAR(K58),"") -> 2024 | AD58: =IF(NOT(ISBLANK(A58)),YEAR(A58),"") -> 2024 | AE58: =IF(NOT(ISBLANK(L58)),YEAR(L58),"") | AF58: =IF(NOT(ISBLANK(L58)),MONTH(L58),"")
A59: 45408 | B59: 1045 | C59: Daniel Calderísta | F59: Placa de caldera | G59: Ariston | H59: Microcombi (CMP-BT-TEC HS) | I59: 060102901323 | K59: 45418 | L59: 45419 | M59: 206 | N59: 166000 | O59: Enviado | P59: Reparado | Q59: Aceptado | R59: =IF(Q59="Aceptado",N59,0) -> 166000 | S59: 166000 | T59: =IFERROR(+T58+R59-S59,0) -> 0 | U59: =IF(NOT(ISBLANK(K59)),MONTH(K59),"") -> 5 | V59: =IF(NOT(ISBLANK(A59)),MONTH(A59),"") -> 4 | W59: =IFERROR(+S59-R59,0) -> 0 | X59: Diego | Z59: 710 | AC59: =IF(NOT(ISBLANK(K59)),YEAR(K59),"") -> 2024 | AD59: =IF(NOT(ISBLANK(A59)),YEAR(A59),"") -> 2024 | AE59: =IF(NOT(ISBLANK(L59)),YEAR(L59),"") -> 2024 | AF59: =IF(NOT(ISBLANK(L59)),MONTH(L59),"") -> 5
A60: 45408 | B60: 1046 | C60: Concejo Municipal de Bariloche | F60: Placa de caldera | G60: Rehau | H60: Antea 24 (CE-0051BS3297) | I60: 5016 | K60: 45411 | L60: 45411 | M60: 200 | N60: 179500 | O60: Enviado | P60: Reparado | Q60: Aceptado | R60: =IF(Q60="Aceptado",N60,0) -> 179500 | S60: 179500 | T60: =IFERROR(+T59+R60-S60,0) -> 0 | U60: =IF(NOT(ISBLANK(K60)),MONTH(K60),"") -> 4 | V60: =IF(NOT(ISBLANK(A60)),MONTH(A60),"") -> 4 | W60: =IFERROR(+S60-R60,0) -> 0 | X60: Diego | Z60: 707 | AA60: 00001-00000307 | AC60: =IF(NOT(ISBLANK(K60)),YEAR(K60),"") -> 2024 | AD60: =IF(NOT(ISBLANK(A60)),YEAR(A60),"") -> 2024 | AE60: =IF(NOT(ISBLANK(L60)),YEAR(L60),"") -> 2024 | AF60: =IF(NOT(ISBLANK(L60)),MONTH(L60),"") -> 4
A61: 45412 | B61: 1047 | C61: Facundo | F61: Placa de calefactor por aire | G61: Westric (Multicontrol) | H61: CG-050-GAC1ANS(CC710A-V1,0 | I61: 54-1139-04 | K61: 45412 | L61: 45412 | M61: 207 | N61: 166000 | O61: Enviado | P61: Reparado | Q61: Aceptado | R61: =IF(Q61="Aceptado",N61,0) -> 166000 | S61: 166000 | T61: =IFERROR(+T60+R61-S61,0) -> 0 | U61: =IF(NOT(ISBLANK(K61)),MONTH(K61),"") -> 4 | V61: =IF(NOT(ISBLANK(A61)),MONTH(A61),"") -> 4 | W61: =IFERROR(+S61-R61,0) -> 0 | X61: Diego | Z61: 708 | AC61: =IF(NOT(ISBLANK(K61)),YEAR(K61),"") -> 2024 | AD61: =IF(NOT(ISBLANK(A61)),YEAR(A61),"") -> 2024 | AE61: =IF(NOT(ISBLANK(L61)),YEAR(L61),"") -> 2024 | AF61: =IF(NOT(ISBLANK(L61)),MONTH(L61),"") -> 4
A62: 45414 | B62: 1048 | C62: Javier | F62: TV LED 39" | G62: Philips | H62: 39PFG4109 77 | I62: ZA1A1449002884 | K62: 45435 | L62: 45435 | M62: 0 | N62: 0 | O62: BRC | P62: Sin Reparación | Q62: Aceptado | R62: =IF(Q62="Aceptado",N62,0) -> 0 | S62: 0 | T62: =IFERROR(+T61+R62-S62,0) -> 0 | U62: =IF(NOT(ISBLANK(K62)),MONTH(K62),"") -> 5 | V62: =IF(NOT(ISBLANK(A62)),MONTH(A62),"") -> 5 | W62: =IFERROR(+S62-R62,0) -> 0 | X62: Diego | AC62: =IF(NOT(ISBLANK(K62)),YEAR(K62),"") -> 2024 | AD62: =IF(NOT(ISBLANK(A62)),YEAR(A62),"") -> 2024 | AE62: =IF(NOT(ISBLANK(L62)),YEAR(L62),"") -> 2024 | AF62: =IF(NOT(ISBLANK(L62)),MONTH(L62),"") -> 5
A63: 45415 | B63: 1049 | C63: Facundo | F63: Placa de calefactor por aire | G63: Westric (Multicontrol) | H63: CG-050-GAC1ANS(CC710A-V1,0 | I63: 80C27104 | K63: 45415 | L63: 45419 | M63: 180 | N63: 166000 | O63: Enviado | P63: Reparado | Q63: Aceptado | R63: =IF(Q63="Aceptado",N63,0) -> 166000 | S63: 166000 | T63: =IFERROR(+T62+R63-S63,0) -> 0 | U63: =IF(NOT(ISBLANK(K63)),MONTH(K63),"") -> 5 | V63: =IF(NOT(ISBLANK(A63)),MONTH(A63),"") -> 5 | W63: =IFERROR(+S63-R63,0) -> 0 | X63: Diego | Z63: 709 | AC63: =IF(NOT(ISBLANK(K63)),YEAR(K63),"") -> 2024 | AD63: =IF(NOT(ISBLANK(A63)),YEAR(A63),"") -> 2024 | AE63: =IF(NOT(ISBLANK(L63)),YEAR(L63),"") -> 2024 | AF63: =IF(NOT(ISBLANK(L63)),MONTH(L63),"") -> 5
A64: 45418 | B64: 1050 | C64: ELS | D64: MDP | F64: Fuente de alimentación | G64: General Electric | H64: DS3820PSCB1C1B | I64: R24165 | K64: 45434 | L64: 45429 | M64: 805 | N64: 741900 | O64: Enviado | P64: Reparado | Q64: Aceptado | R64: =IF(Q64="Aceptado",N64,0) -> 741900 | S64: 741900 | T64: =IFERROR(+T63+R64-S64,0) -> 0 | U64: =IF(NOT(ISBLANK(K64)),MONTH(K64),"") -> 5 | V64: =IF(NOT(ISBLANK(A64)),MONTH(A64),"") -> 5 | W64: =IFERROR(+S64-R64,0) -> 0 | X64: Diego | AA64: 00001-00000330 | AC64: =IF(NOT(ISBLANK(K64)),YEAR(K64),"") -> 2024 | AD64: =IF(NOT(ISBLANK(A64)),YEAR(A64),"") -> 2024 | AE64: =IF(NOT(ISBLANK(L64)),YEAR(L64),"") -> 2024 | AF64: =IF(NOT(ISBLANK(L64)),MONTH(L64),"") -> 5
A65: 45418 | B65: 1051 | C65: ELS | D65: MDP | F65: Placa CPU HMPJ | G65: General Electric | H65: DS3800HMPJ1A1D | I65: 0A37A4 | K65: 45434 | L65: 45429 | M65: 325 | N65: 299820 | O65: Enviado | P65: Reparado | Q65: Aceptado | R65: =IF(Q65="Aceptado",N65,0) -> 299820 | S65: 299820 | T65: =IFERROR(+T64+R65-S65,0) -> 0 | U65: =IF(NOT(ISBLANK(K65)),MONTH(K65),"") -> 5 | V65: =IF(NOT(ISBLANK(A65)),MONTH(A65),"") -> 5 | W65: =IFERROR(+S65-R65,0) -> 0 | X65: Diego | AA65: 00001-00000331 | AC65: =IF(NOT(ISBLANK(K65)),YEAR(K65),"") -> 2024 | AD65: =IF(NOT(ISBLANK(A65)),YEAR(A65),"") -> 2024 | AE65: =IF(NOT(ISBLANK(L65)),YEAR(L65),"") -> 2024 | AF65: =IF(NOT(ISBLANK(L65)),MONTH(L65),"") -> 5
A66: 45418 | B66: 1052 | C66: Ariel (Placa lavarropas) | F66: Placa de Lavarropas | G66: Appliance Control | H66: 7722001000 | I66: 529164401293 | K66: 45419 | L66: 45419 | M66: 16 | N66: 15000 | O66: Enviado | P66: Sin Falla | Q66: Aceptado | R66: =IF(Q66="Aceptado",N66,0) -> 15000 | S66: 15000 | T66: =IFERROR(+T65+R66-S66,0) -> 0 | U66: =IF(NOT(ISBLANK(K66)),MONTH(K66),"") -> 5 | V66: =IF(NOT(ISBLANK(A66)),MONTH(A66),"") -> 5 | W66: =IFERROR(+S66-R66,0) -> 0 | X66: Diego | AC66: =IF(NOT(ISBLANK(K66)),YEAR(K66),"") -> 2024 | AD66: =IF(NOT(ISBLANK(A66)),YEAR(A66),"") -> 2024 | AE66: =IF(NOT(ISBLANK(L66)),YEAR(L66),"") -> 2024 | AF66: =IF(NOT(ISBLANK(L66)),MONTH(L66),"") -> 5
A67: 45420 | B67: 1053 | C67: Daniel Calderísta | F67: Placa de caldera | G67: Caldaia | H67: Genius S30 (11600011) | I67: DD3V5 | K67: 45420 | L67: 45421 | M67: 139 | N67: 112500 | O67: Enviado | P67: Reparado | Q67: Aceptado | R67: =IF(Q67="Aceptado",N67,0) -> 112500 | S67: 112500 | T67: =IFERROR(+T66+R67-S67,0) -> 0 | U67: =IF(NOT(ISBLANK(K67)),MONTH(K67),"") -> 5 | V67: =IF(NOT(ISBLANK(A67)),MONTH(A67),"") -> 5 | W67: =IFERROR(+S67-R67,0) -> 0 | X67: Diego | Z67: 712 | AC67: =IF(NOT(ISBLANK(K67)),YEAR(K67),"") -> 2024 | AD67: =IF(NOT(ISBLANK(A67)),YEAR(A67),"") -> 2024 | AE67: =IF(NOT(ISBLANK(L67)),YEAR(L67),"") -> 2024 | AF67: =IF(NOT(ISBLANK(L67)),MONTH(L67),"") -> 5
A68: 45420 | B68: 1054 | C68: Facundo | F68: Placa de caldera | G68: Neobit Plus (Baxi) | H68: Aequator(CS0261F) | I68: 50056809-001 | K68: 45420 | L68: 45420 | M68: 192 | N68: 173500 | O68: Enviado | P68: Reparado | Q68: Aceptado | R68: =IF(Q68="Aceptado",N68,0) -> 173500 | S68: 173500 | T68: =IFERROR(+T67+R68-S68,0) -> 0 | U68: =IF(NOT(ISBLANK(K68)),MONTH(K68),"") -> 5 | V68: =IF(NOT(ISBLANK(A68)),MONTH(A68),"") -> 5 | W68: =IFERROR(+S68-R68,0) -> 0 | X68: Diego | Z68: 711 | AC68: =IF(NOT(ISBLANK(K68)),YEAR(K68),"") -> 2024 | AD68: =IF(NOT(ISBLANK(A68)),YEAR(A68),"") -> 2024 | AE68: =IF(NOT(ISBLANK(L68)),YEAR(L68),"") -> 2024 | AF68: =IF(NOT(ISBLANK(L68)),MONTH(L68),"") -> 5
A69: 45421 | B69: 1055 | C69: Daniel (Bari Clima) | F69: Programador De Llama + bastidor y placa conectores | G69: Sit | H69: 537 ABC | I69: 17-37-0593 | K69: 45425 | L69: 45425 | M69: 216 | N69: 175500 | O69: Enviado | P69: Reparado | Q69: Aceptado | R69: =IF(Q69="Aceptado",N69,0) -> 175500 | S69: 175500 | T69: =IFERROR(+T68+R69-S69,0) -> 0 | U69: =IF(NOT(ISBLANK(K69)),MONTH(K69),"") -> 5 | V69: =IF(NOT(ISBLANK(A69)),MONTH(A69),"") -> 5 | W69: =IFERROR(+S69-R69,0) -> 0 | X69: Diego | Z69: 713 | AC69: =IF(NOT(ISBLANK(K69)),YEAR(K69),"") -> 2024 | AD69: =IF(NOT(ISBLANK(A69)),YEAR(A69),"") -> 2024 | AE69: =IF(NOT(ISBLANK(L69)),YEAR(L69),"") -> 2024 | AF69: =IF(NOT(ISBLANK(L69)),MONTH(L69),"") -> 5
A70: 45422 | B70: 1056 | C70: Elvis | F70: Placa de Lavarropas | G70: Candy | H70: Vita Smart Cvst 810 T(E41052140) | I70: 41045072 | K70: 45441 | L70: 45427 | M70: 147 | N70: 133500 | O70: Enviado | P70: Reparado | Q70: Aceptado | R70: =IF(Q70="Aceptado",N70,0) -> 133500 | S70: 133500 | T70: =IFERROR(+T69+R70-S70,0) -> 0 | U70: =IF(NOT(ISBLANK(K70)),MONTH(K70),"") -> 5 | V70: =IF(NOT(ISBLANK(A70)),MONTH(A70),"") -> 5 | W70: =IFERROR(+S70-R70,0) -> 0 | X70: Diego | Z70: 719 | AC70: =IF(NOT(ISBLANK(K70)),YEAR(K70),"") -> 2024 | AD70: =IF(NOT(ISBLANK(A70)),YEAR(A70),"") -> 2024 | AE70: =IF(NOT(ISBLANK(L70)),YEAR(L70),"") -> 2024 | AF70: =IF(NOT(ISBLANK(L70)),MONTH(L70),"") -> 5
A71: 45423 | B71: 1057 | C71: Julio Piacentini | F71: Inverter 48vdc / 220vac - 5000W | G71: Megared | H71: PINC-48-5000-OFF-PWM-S | I71: 92931905104952 | K71: 45437 | L71: 45427 | M71: 450 | N71: 409500 | O71: Enviado | P71: Reparado | Q71: Aceptado | R71: =IF(Q71="Aceptado",N71,0) -> 409500 | S71: 409500 | T71: =IFERROR(+T70+R71-S71,0) -> 0 | U71: =IF(NOT(ISBLANK(K71)),MONTH(K71),"") -> 5 | V71: =IF(NOT(ISBLANK(A71)),MONTH(A71),"") -> 5 | W71: =IFERROR(+S71-R71,0) -> 0 | X71: Diego | Z71: 718 | AC71: =IF(NOT(ISBLANK(K71)),YEAR(K71),"") -> 2024 | AD71: =IF(NOT(ISBLANK(A71)),YEAR(A71),"") -> 2024 | AE71: =IF(NOT(ISBLANK(L71)),YEAR(L71),"") -> 2024 | AF71: =IF(NOT(ISBLANK(L71)),MONTH(L71),"") -> 5
A72: 45427 | B72: 1058 | C72: ELS | D72: MDP | E72: Coarco BRC | F72: Panel de control | G72: Olympian | H72: Power wizard 1.1 (449-2590-00) | I72: 1044E724TZ | J72: 23740 | K72: 45427 | L72: 45429 | M72: 515 | N72: 470859 | O72: Enviado | P72: Reparado | Q72: Aceptado | R72: =IF(Q72="Aceptado",N72,0) -> 470859 | S72: 470859 | T72: =IFERROR(+T71+R72-S72,0) -> 0 | U72: =IF(NOT(ISBLANK(K72)),MONTH(K72),"") -> 5 | V72: =IF(NOT(ISBLANK(A72)),MONTH(A72),"") -> 5 | W72: =IFERROR(+S72-R72,0) -> 0 | X72: Diego | AA72: 00001-00000321 | AC72: =IF(NOT(ISBLANK(K72)),YEAR(K72),"") -> 2024 | AD72: =IF(NOT(ISBLANK(A72)),YEAR(A72),"") -> 2024 | AE72: =IF(NOT(ISBLANK(L72)),YEAR(L72),"") -> 2024 | AF72: =IF(NOT(ISBLANK(L72)),MONTH(L72),"") -> 5
A73: 45427 | B73: 1059 | C73: C.U.B.A Sede Cerro Catedral | F73: Estabilizador de tensión 3000W | G73: Lyonn | H73: TCA-3000NV | I73: 918316069300210 | K73: 45428 | L73: 45432 | M73: 104 | N73: 95000 | O73: Enviado | P73: Reparado | Q73: Aceptado | R73: =IF(Q73="Aceptado",N73,0) -> 95000 | S73: 95000 | T73: =IFERROR(+T72+R73-S73,0) -> 0 | U73: =IF(NOT(ISBLANK(K73)),MONTH(K73),"") -> 5 | V73: =IF(NOT(ISBLANK(A73)),MONTH(A73),"") -> 5 | W73: =IFERROR(+S73-R73,0) -> 0 | X73: Diego | AC73: =IF(NOT(ISBLANK(K73)),YEAR(K73),"") -> 2024 | AD73: =IF(NOT(ISBLANK(A73)),YEAR(A73),"") -> 2024 | AE73: =IF(NOT(ISBLANK(L73)),YEAR(L73),"") -> 2024 | AF73: =IF(NOT(ISBLANK(L73)),MONTH(L73),"") -> 5
A74: 45427 | B74: 1060 | C74: Ascensores Bariloche | F74: Placa de ascensor | G74: Automac | H74: A6220v4 | I74: 25477 | K74: 45427 | L74: 45444 | M74: 0 | N74: 0 | O74: Enviado | P74: Sin Reparación | Q74: Aceptado | R74: =IF(Q74="Aceptado",N74,0) -> 0 | S74: 0 | T74: =IFERROR(+T73+R74-S74,0) -> 0 | U74: =IF(NOT(ISBLANK(K74)),MONTH(K74),"") -> 5 | V74: =IF(NOT(ISBLANK(A74)),MONTH(A74),"") -> 5 | W74: =IFERROR(+S74-R74,0) -> 0 | X74: Diego | AC74: =IF(NOT(ISBLANK(K74)),YEAR(K74),"") -> 2024 | AD74: =IF(NOT(ISBLANK(A74)),YEAR(A74),"") -> 2024 | AE74: =IF(NOT(ISBLANK(L74)),YEAR(L74),"") -> 2024 | AF74: =IF(NOT(ISBLANK(L74)),MONTH(L74),"") -> 6
A75: 45427 | B75: 1061 | C75: Ascensores Bariloche | F75: Placa Fuente de ascensor | G75: Automac | H75: A6210 | I75: A7422B | K75: 45427 | L75: 45427 | M75: 54 | N75: 48500 | O75: Enviado | P75: Reparado | Q75: Aceptado | R75: =IF(Q75="Aceptado",N75,0) -> 48500 | S75: 48500 | T75: =IFERROR(+T74+R75-S75,0) -> 0 | U75: =IF(NOT(ISBLANK(K75)),MONTH(K75),"") -> 5 | V75: =IF(NOT(ISBLANK(A75)),MONTH(A75),"") -> 5 | W75: =IFERROR(+S75-R75,0) -> 0 | X75: Diego | Z75: 716 | AC75: =IF(NOT(ISBLANK(K75)),YEAR(K75),"") -> 2024 | AD75: =IF(NOT(ISBLANK(A75)),YEAR(A75),"") -> 2024 | AE75: =IF(NOT(ISBLANK(L75)),YEAR(L75),"") -> 2024 | AF75: =IF(NOT(ISBLANK(L75)),MONTH(L75),"") -> 5
A76: 45428 | B76: 1062 | C76: Facundo | F76: Controlador de caldera eléctrica | G76: Peisa | H76: EKCO.LN2 | I76: 01-2016 | K76: 45428 | L76: 45432 | M76: 203 | N76: 166500 | O76: Enviado | P76: Reparado | Q76: Aceptado | R76: =IF(Q76="Aceptado",N76,0) -> 166500 | S76: 166500 | T76: =IFERROR(+T75+R76-S76,0) -> 0 | U76: =IF(NOT(ISBLANK(K76)),MONTH(K76),"") -> 5 | V76: =IF(NOT(ISBLANK(A76)),MONTH(A76),"") -> 5 | W76: =IFERROR(+S76-R76,0) -> 0 | X76: Diego | Z76: 715 | AC76: =IF(NOT(ISBLANK(K76)),YEAR(K76),"") -> 2024 | AD76: =IF(NOT(ISBLANK(A76)),YEAR(A76),"") -> 2024 | AE76: =IF(NOT(ISBLANK(L76)),YEAR(L76),"") -> 2024 | AF76: =IF(NOT(ISBLANK(L76)),MONTH(L76),"") -> 5
A77: 45428 | B77: 1063 | C77: Connie Santana | F77: UPS 800W | G77: Kaise | H77: micro800 | I77: 3100127277D20711300344 | K77: 45441 | L77: 45441 | M77: 96 | N77: 96450 | O77: Enviado | P77: Reparado | Q77: Aceptado | R77: =IF(Q77="Aceptado",N77,0) -> 96450 | S77: 96450 | T77: =IFERROR(+T76+R77-S77,0) -> 0 | U77: =IF(NOT(ISBLANK(K77)),MONTH(K77),"") -> 5 | V77: =IF(NOT(ISBLANK(A77)),MONTH(A77),"") -> 5 | W77: =IFERROR(+S77-R77,0) -> 0 | X77: Diego | Z77: 720 | AA77: 00001-00000029 | AC77: =IF(NOT(ISBLANK(K77)),YEAR(K77),"") -> 2024 | AD77: =IF(NOT(ISBLANK(A77)),YEAR(A77),"") -> 2024 | AE77: =IF(NOT(ISBLANK(L77)),YEAR(L77),"") -> 2024 | AF77: =IF(NOT(ISBLANK(L77)),MONTH(L77),"") -> 5
A78: 45429.125 | B78: 1064 | C78: Facundo | F78: Ventilador de caldera de condensación | G78: Sit | H78: NG40 | I78: 195224 | K78: 45432.125 | L78: 45432.125 | M78: 160 | N78: 130500 | O78: Enviado | P78: Reparado | Q78: Aceptado | R78: =IF(Q78="Aceptado",N78,0) -> 130500 | S78: 130500 | T78: =IFERROR(+T77+R78-S78,0) -> 0 | U78: =IF(NOT(ISBLANK(K78)),MONTH(K78),"") -> 5 | V78: =IF(NOT(ISBLANK(A78)),MONTH(A78),"") -> 5 | W78: =IFERROR(+S78-R78,0) -> 0 | X78: Diego | Z78: 715 | AC78: =IF(NOT(ISBLANK(K78)),YEAR(K78),"") -> 2024 | AD78: =IF(NOT(ISBLANK(A78)),YEAR(A78),"") -> 2024 | AE78: =IF(NOT(ISBLANK(L78)),YEAR(L78),"") -> 2024 | AF78: =IF(NOT(ISBLANK(L78)),MONTH(L78),"") -> 5
A79: 45433 | B79: 1065 | C79: C.U.B.A Sede Cerro Catedral | F79: Placas controladoras de Horno convector | G79: Brafh | H79: HC-820 | I79: GAPSR | K79: 45435 | L79: 45433 | M79: 140 | N79: 127500 | O79: Enviado | P79: Reparado | Q79: Aceptado | R79: =IF(Q79="Aceptado",N79,0) -> 127500 | S79: 127500 | T79: =IFERROR(+T78+R79-S79,0) -> 0 | U79: =IF(NOT(ISBLANK(K79)),MONTH(K79),"") -> 5 | V79: =IF(NOT(ISBLANK(A79)),MONTH(A79),"") -> 5 | W79: =IFERROR(+S79-R79,0) -> 0 | X79: Diego | Z79: 717 | AC79: =IF(NOT(ISBLANK(K79)),YEAR(K79),"") -> 2024 | AD79: =IF(NOT(ISBLANK(A79)),YEAR(A79),"") -> 2024 | AE79: =IF(NOT(ISBLANK(L79)),YEAR(L79),"") -> 2024 | AF79: =IF(NOT(ISBLANK(L79)),MONTH(L79),"") -> 5
A80: 45433.125 | B80: 1066 | C80: Daniel Calderísta | F80: Placa de caldera | G80: Caldaia | H80: Genius M30 (11600011) | I80: 4IT4B | K80: 45433.125 | M80: 152 | N80: 137500 | O80: BRC | P80: Reparado | Q80: A la Espera de Aceptación | R80: =IF(Q80="Aceptado",N80,0) -> 0 | S80: 0 | T80: =IFERROR(+T79+R80-S80,0) -> 0 | U80: =IF(NOT(ISBLANK(K80)),MONTH(K80),"") -> 5 | V80: =IF(NOT(ISBLANK(A80)),MONTH(A80),"") -> 5 | W80: =IFERROR(+S80-R80,0) -> 0 | X80: Diego | AC80: =IF(NOT(ISBLANK(K80)),YEAR(K80),"") -> 2024 | AD80: =IF(NOT(ISBLANK(A80)),YEAR(A80),"") -> 2024 | AE80: =IF(NOT(ISBLANK(L80)),YEAR(L80),"") | AF80: =IF(NOT(ISBLANK(L80)),MONTH(L80),"")
A81: 45441 | B81: 1067 | C81: Convertec-Energías Renovables Bariloche | F81: Inversor / Cargador Solar 1KW | G81: Must | H81: PV18-1012 VPM | I81: VPV181012202103270117 | K81: 45441 | L81: 45446 | M81: 200 | N81: 186000 | O81: Enviado | P81: Reparado | Q81: Aceptado | R81: =IF(Q81="Aceptado",N81,0) -> 186000 | S81: 186000 | T81: =IFERROR(+T80+R81-S81,0) -> 0 | U81: =IF(NOT(ISBLANK(K81)),MONTH(K81),"") -> 5 | V81: =IF(NOT(ISBLANK(A81)),MONTH(A81),"") -> 5 | W81: =IFERROR(+S81-R81,0) -> 0 | X81: Diego | Z81: 721 | AC81: =IF(NOT(ISBLANK(K81)),YEAR(K81),"") -> 2024 | AD81: =IF(NOT(ISBLANK(A81)),YEAR(A81),"") -> 2024 | AE81: =IF(NOT(ISBLANK(L81)),YEAR(L81),"") -> 2024 | AF81: =IF(NOT(ISBLANK(L81)),MONTH(L81),"") -> 6
A82: 45441 | B82: 1068 | C82: Patagonia Clima SAS | F82: Placa de caldera | G82: Peisa | H82: 100-02 | I82: 12517-000OB | K82: 45441 | L82: 45446 | M82: 166 | N82: 155000 | O82: Enviado | P82: Reparado | Q82: Aceptado | R82: =IF(Q82="Aceptado",N82,0) -> 155000 | S82: 155000 | T82: =IFERROR(+T81+R82-S82,0) -> 0 | U82: =IF(NOT(ISBLANK(K82)),MONTH(K82),"") -> 5 | V82: =IF(NOT(ISBLANK(A82)),MONTH(A82),"") -> 5 | W82: =IFERROR(+S82-R82,0) -> 0 | X82: Diego | Z82: 722 | AC82: =IF(NOT(ISBLANK(K82)),YEAR(K82),"") -> 2024 | AD82: =IF(NOT(ISBLANK(A82)),YEAR(A82),"") -> 2024 | AE82: =IF(NOT(ISBLANK(L82)),YEAR(L82),"") -> 2024 | AF82: =IF(NOT(ISBLANK(L82)),MONTH(L82),"") -> 6
A83: 45442 | B83: 1069 | C83: Convertec-Energías Renovables Bariloche | F83: UPS + Inversor + Cargador | G83: Energit | H83: UPS-POWER SINE 1500-12 | I83: EP30001512C201705140009 | K83: 45446 | L83: 45446 | M83: 252 | N83: 235000 | O83: Enviado | P83: Reparado | Q83: Aceptado | R83: =IF(Q83="Aceptado",N83,0) -> 235000 | S83: 235000 | T83: =IFERROR(+T82+R83-S83,0) -> 0 | U83: =IF(NOT(ISBLANK(K83)),MONTH(K83),"") -> 6 | V83: =IF(NOT(ISBLANK(A83)),MONTH(A83),"") -> 5 | W83: =IFERROR(+S83-R83,0) -> 0 | X83: Diego | Z83: 723 | AC83: =IF(NOT(ISBLANK(K83)),YEAR(K83),"") -> 2024 | AD83: =IF(NOT(ISBLANK(A83)),YEAR(A83),"") -> 2024 | AE83: =IF(NOT(ISBLANK(L83)),YEAR(L83),"") -> 2024 | AF83: =IF(NOT(ISBLANK(L83)),MONTH(L83),"") -> 6
A84: 45442 | B84: 1070 | C84: Maxi (Servicios Carlitos) | F84: Smart TV 49" | G84: Skyworth | H84: SW49S6SUG | I84: 18-99005165-L1 | K84: 45447 | L84: 45447 | M84: 210 | N84: 209000 | O84: Enviado | P84: No Aceptaron Reparación | Q84: NO Aceptado | R84: =IF(Q84="Aceptado",N84,0) -> 0 | S84: 0 | T84: =IFERROR(+T83+R84-S84,0) -> 0 | U84: =IF(NOT(ISBLANK(K84)),MONTH(K84),"") -> 6 | V84: =IF(NOT(ISBLANK(A84)),MONTH(A84),"") -> 5 | W84: =IFERROR(+S84-R84,0) -> 0 | X84: Diego | AC84: =IF(NOT(ISBLANK(K84)),YEAR(K84),"") -> 2024 | AD84: =IF(NOT(ISBLANK(A84)),YEAR(A84),"") -> 2024 | AE84: =IF(NOT(ISBLANK(L84)),YEAR(L84),"") -> 2024 | AF84: =IF(NOT(ISBLANK(L84)),MONTH(L84),"") -> 6
A85: 45443 | B85: 1071 | C85: C.U.B.A Sede Cerro Catedral | F85: Amplificador de audio | G85: SKP | H85: MAX-320 | I85: 07241400458 | K85: 45443 | L85: 45446 | M85: 16 | N85: 15000 | O85: BRC | P85: Sin Reparación | Q85: Aceptado | R85: =IF(Q85="Aceptado",N85,0) -> 15000 | S85: 0 | T85: =IFERROR(+T84+R85-S85,0) -> 15000 | U85: =IF(NOT(ISBLANK(K85)),MONTH(K85),"") -> 5 | V85: =IF(NOT(ISBLANK(A85)),MONTH(A85),"") -> 5 | W85: =IFERROR(+S85-R85,0) -> -15000 | X85: Diego | AC85: =IF(NOT(ISBLANK(K85)),YEAR(K85),"") -> 2024 | AD85: =IF(NOT(ISBLANK(A85)),YEAR(A85),"") -> 2024 | AE85: =IF(NOT(ISBLANK(L85)),YEAR(L85),"") -> 2024 | AF85: =IF(NOT(ISBLANK(L85)),MONTH(L85),"") -> 6
A86: 45446 | B86: 1072 | C86: Patagonia Clima SAS | F86: Placa de Caldera + display | G86: Peisa | H86: BGL 188 - PR00705 V1.5 | I86: 141209657/2022/02/11 | K86: 45446 | L86: 45449 | M86: 182 | N86: 170000 | O86: Enviado | P86: Reparado | Q86: Aceptado | R86: =IF(Q86="Aceptado",N86,0) -> 170000 | S86: 170000 | T86: =IFERROR(+T85+R86-S86,0) -> 15000 | U86: =IF(NOT(ISBLANK(K86)),MONTH(K86),"") -> 6 | V86: =IF(NOT(ISBLANK(A86)),MONTH(A86),"") -> 6 | W86: =IFERROR(+S86-R86,0) -> 0 | X86: Diego | Z86: 724 | AC86: =IF(NOT(ISBLANK(K86)),YEAR(K86),"") -> 2024 | AD86: =IF(NOT(ISBLANK(A86)),YEAR(A86),"") -> 2024 | AE86: =IF(NOT(ISBLANK(L86)),YEAR(L86),"") -> 2024 | AF86: =IF(NOT(ISBLANK(L86)),MONTH(L86),"") -> 6
A87: 45447.125 | B87: 1073 | C87: Leandro Slosel | F87: Panel de Unidad de transferencia automática | G87: GenParts TSI | H87: A52Z2-H | I87: 2007A 2140 | K87: 45451.125 | L87: 45451.125 | M87: 230 | N87: 213900 | O87: Enviado | P87: Reparado | Q87: Aceptado | R87: =IF(Q87="Aceptado",N87,0) -> 213900 | S87: 213900 | T87: =IFERROR(+T86+R87-S87,0) -> 15000 | U87: =IF(NOT(ISBLANK(K87)),MONTH(K87),"") -> 6 | V87: =IF(NOT(ISBLANK(A87)),MONTH(A87),"") -> 6 | W87: =IFERROR(+S87-R87,0) -> 0 | X87: Diego | Z87: 726 | AA87: 00001-00000028 | AC87: =IF(NOT(ISBLANK(K87)),YEAR(K87),"") -> 2024 | AD87: =IF(NOT(ISBLANK(A87)),YEAR(A87),"") -> 2024 | AE87: =IF(NOT(ISBLANK(L87)),YEAR(L87),"") -> 2024 | AF87: =IF(NOT(ISBLANK(L87)),MONTH(L87),"") -> 6
A88: 45448 | B88: 1074 | C88: ELS | D88: MDP | E88: Hotel Llao Llao | F88: Variador de velocidad 10HP | G88: LS | H88: SV075iS5-4NO | I88: 61110006W0 | K88: 45448 | L88: 45463 | M88: 436 | N88: 409605 | O88: Enviado | P88: Reparado | Q88: Aceptado | R88: =IF(Q88="Aceptado",N88,0) -> 409605 | S88: 409605 | T88: =IFERROR(+T87+R88-S88,0) -> 15000 | U88: =IF(NOT(ISBLANK(K88)),MONTH(K88),"") -> 6 | V88: =IF(NOT(ISBLANK(A88)),MONTH(A88),"") -> 6 | W88: =IFERROR(+S88-R88,0) -> 0 | X88: Diego | AA88: 00001-00000322 | AC88: =IF(NOT(ISBLANK(K88)),YEAR(K88),"") -> 2024 | AD88: =IF(NOT(ISBLANK(A88)),YEAR(A88),"") -> 2024 | AE88: =IF(NOT(ISBLANK(L88)),YEAR(L88),"") -> 2024 | AF88: =IF(NOT(ISBLANK(L88)),MONTH(L88),"") -> 6
A89: 45450 | B89: 1075 | C89: Daniel (Bari Clima) | F89: Placa de Caldera | G89: Caldaia | H89: E321060 (TOP a perilla) | I89: LP29B | K89: 45451 | L89: 45451 | M89: 170 | N89: 142000 | O89: Enviado | P89: Reparado | Q89: Aceptado | R89: =IF(Q89="Aceptado",N89,0) -> 142000 | S89: 142000 | T89: =IFERROR(+T88+R89-S89,0) -> 15000 | U89: =IF(NOT(ISBLANK(K89)),MONTH(K89),"") -> 6 | V89: =IF(NOT(ISBLANK(A89)),MONTH(A89),"") -> 6 | W89: =IFERROR(+S89-R89,0) -> 0 | X89: Diego | Z89: 725 | AC89: =IF(NOT(ISBLANK(K89)),YEAR(K89),"") -> 2024 | AD89: =IF(NOT(ISBLANK(A89)),YEAR(A89),"") -> 2024 | AE89: =IF(NOT(ISBLANK(L89)),YEAR(L89),"") -> 2024 | AF89: =IF(NOT(ISBLANK(L89)),MONTH(L89),"") -> 6
A90: 45450.125 | B90: 1076 | C90: José Groznik | F90: Control de temperatura | G90: Hidromotor | H90: TK10901C | I90: 05081364 | K90: 45457.125 | L90: 45451.125 | M90: 85 | N90: 86500 | O90: Enviado | P90: Reparado | Q90: Aceptado | R90: =IF(Q90="Aceptado",N90,0) -> 86500 | S90: 86500 | T90: =IFERROR(+T89+R90-S90,0) -> 15000 | U90: =IF(NOT(ISBLANK(K90)),MONTH(K90),"") -> 6 | V90: =IF(NOT(ISBLANK(A90)),MONTH(A90),"") -> 6 | W90: =IFERROR(+S90-R90,0) -> 0 | X90: Diego | Z90: 727 | AA90: 00000-00000000 | AC90: =IF(NOT(ISBLANK(K90)),YEAR(K90),"") -> 2024 | AD90: =IF(NOT(ISBLANK(A90)),YEAR(A90),"") -> 2024 | AE90: =IF(NOT(ISBLANK(L90)),YEAR(L90),"") -> 2024 | AF90: =IF(NOT(ISBLANK(L90)),MONTH(L90),"") -> 6
A91: 45451 | B91: 1077 | C91: Colegio San Esteban Bariloche | F91: Soldadora inverter MIG | G91: Hugong Welder | H91: MIG 160 | I91: 1OPAV | K91: 45456 | L91: 45454 | M91: 250 | N91: 235000 | O91: Enviado | P91: Reparado | Q91: Aceptado | R91: =IF(Q91="Aceptado",N91,0) -> 235000 | S91: 235000 | T91: =IFERROR(+T90+R91-S91,0) -> 15000 | U91: =IF(NOT(ISBLANK(K91)),MONTH(K91),"") -> 6 | V91: =IF(NOT(ISBLANK(A91)),MONTH(A91),"") -> 6 | W91: =IFERROR(+S91-R91,0) -> 0 | X91: Diego | AC91: =IF(NOT(ISBLANK(K91)),YEAR(K91),"") -> 2024 | AD91: =IF(NOT(ISBLANK(A91)),YEAR(A91),"") -> 2024 | AE91: =IF(NOT(ISBLANK(L91)),YEAR(L91),"") -> 2024 | AF91: =IF(NOT(ISBLANK(L91)),MONTH(L91),"") -> 6
A92: 45453 | B92: 1078 | C92: Christian Steverlynck | F92: Cargador de Batería 12v 20A | G92: Enertik | H92: EC-20-12 | I92: EC2012S076 | K92: 45476 | L92: 45454 | M92: 100 | N92: 95000 | O92: Enviado | P92: Reparado | Q92: Aceptado | R92: =IF(Q92="Aceptado",N92,0) -> 95000 | S92: 95000 | T92: =IFERROR(+T91+R92-S92,0) -> 15000 | U92: =IF(NOT(ISBLANK(K92)),MONTH(K92),"") -> 7 | V92: =IF(NOT(ISBLANK(A92)),MONTH(A92),"") -> 6 | W92: =IFERROR(+S92-R92,0) -> 0 | X92: Diego | Z92: 732 | AC92: =IF(NOT(ISBLANK(K92)),YEAR(K92),"") -> 2024 | AD92: =IF(NOT(ISBLANK(A92)),YEAR(A92),"") -> 2024 | AE92: =IF(NOT(ISBLANK(L92)),YEAR(L92),"") -> 2024 | AF92: =IF(NOT(ISBLANK(L92)),MONTH(L92),"") -> 6
A93: 45454 | B93: 1079 | C93: Ascensores Bariloche | F93: Cerradura electromagnética | G93: Zuden | H93: ZDL-280 | I93: 334526 | K93: 45454 | L93: 45454 | M93: 50 | N93: 53000 | O93: Enviado | P93: Reparado | Q93: Aceptado | R93: =IF(Q93="Aceptado",N93,0) -> 53000 | S93: 53000 | T93: =IFERROR(+T92+R93-S93,0) -> 15000 | U93: =IF(NOT(ISBLANK(K93)),MONTH(K93),"") -> 6 | V93: =IF(NOT(ISBLANK(A93)),MONTH(A93),"") -> 6 | W93: =IFERROR(+S93-R93,0) -> 0 | X93: Diego | AC93: =IF(NOT(ISBLANK(K93)),YEAR(K93),"") -> 2024 | AD93: =IF(NOT(ISBLANK(A93)),YEAR(A93),"") -> 2024 | AE93: =IF(NOT(ISBLANK(L93)),YEAR(L93),"") -> 2024 | AF93: =IF(NOT(ISBLANK(L93)),MONTH(L93),"") -> 6
A94: 45454 | B94: 1080 | C94: Arturo Ruiz (Comallo) | F94: Inverter 12vdc / 220vac - 600W | G94: Probattery | H94: FI-600/12-CPB | I94: 18D02821 | K94: 45456 | L94: 45456 | M94: 121 | N94: 115000 | O94: Enviado | P94: No Aceptaron Reparación | Q94: NO Aceptado | R94: =IF(Q94="Aceptado",N94,0) -> 0 | S94: 0 | T94: =IFERROR(+T93+R94-S94,0) -> 15000 | U94: =IF(NOT(ISBLANK(K94)),MONTH(K94),"") -> 6 | V94: =IF(NOT(ISBLANK(A94)),MONTH(A94),"") -> 6 | W94: =IFERROR(+S94-R94,0) -> 0 | X94: Diego | AC94: =IF(NOT(ISBLANK(K94)),YEAR(K94),"") -> 2024 | AD94: =IF(NOT(ISBLANK(A94)),YEAR(A94),"") -> 2024 | AE94: =IF(NOT(ISBLANK(L94)),YEAR(L94),"") -> 2024 | AF94: =IF(NOT(ISBLANK(L94)),MONTH(L94),"") -> 6
A95: 45455 | B95: 1081 | C95: Arturo Ruiz (Comallo) | F95: Inverter 12vdc / 220vac - 500W | G95: Probattery | H95: FIOP-500/12V-LI | I95: 2350868ARPB | K95: 45456 | L95: 45456 | M95: 115 | N95: 110000 | O95: Enviado | P95: No Aceptaron Reparación | Q95: NO Aceptado | R95: =IF(Q95="Aceptado",N95,0) -> 0 | S95: 0 | T95: =IFERROR(+T94+R95-S95,0) -> 15000 | U95: =IF(NOT(ISBLANK(K95)),MONTH(K95),"") -> 6 | V95: =IF(NOT(ISBLANK(A95)),MONTH(A95),"") -> 6 | W95: =IFERROR(+S95-R95,0) -> 0 | X95: Diego | AC95: =IF(NOT(ISBLANK(K95)),YEAR(K95),"") -> 2024 | AD95: =IF(NOT(ISBLANK(A95)),YEAR(A95),"") -> 2024 | AE95: =IF(NOT(ISBLANK(L95)),YEAR(L95),"") -> 2024 | AF95: =IF(NOT(ISBLANK(L95)),MONTH(L95),"") -> 6
A96: 45455 | B96: 1082 | C96: Facundo | F96: Climatizador de piscinas | G96: Peisa | H96: T80 | I96: Y05W26L154CE124 | K96: 45481 | L96: 45461 | M96: 210 | N96: 195400 | O96: Enviado | P96: Reparado | Q96: Aceptado | R96: =IF(Q96="Aceptado",N96,0) -> 195400 | S96: 195400 | T96: =IFERROR(+T95+R96-S96,0) -> 15000 | U96: =IF(NOT(ISBLANK(K96)),MONTH(K96),"") -> 7 | V96: =IF(NOT(ISBLANK(A96)),MONTH(A96),"") -> 6 | W96: =IFERROR(+S96-R96,0) -> 0 | X96: Diego | Z96: 734 | AC96: =IF(NOT(ISBLANK(K96)),YEAR(K96),"") -> 2024 | AD96: =IF(NOT(ISBLANK(A96)),YEAR(A96),"") -> 2024 | AE96: =IF(NOT(ISBLANK(L96)),YEAR(L96),"") -> 2024 | AF96: =IF(NOT(ISBLANK(L96)),MONTH(L96),"") -> 6
A97: 45457 | B97: 1083 | C97: Hugo (Soldadora Inverter) | F97: Soldadora inverter 200A | G97: Lincoln | H97: Discovery 225 | I97: DYA26 | K97: 45457 | L97: 45457 | M97: 90 | N97: 88000 | O97: Enviado | P97: Reparado | Q97: Aceptado | R97: =IF(Q97="Aceptado",N97,0) -> 88000 | S97: 88000 | T97: =IFERROR(+T96+R97-S97,0) -> 15000 | U97: =IF(NOT(ISBLANK(K97)),MONTH(K97),"") -> 6 | V97: =IF(NOT(ISBLANK(A97)),MONTH(A97),"") -> 6 | W97: =IFERROR(+S97-R97,0) -> 0 | X97: Diego | Z97: 728 | AC97: =IF(NOT(ISBLANK(K97)),YEAR(K97),"") -> 2024 | AD97: =IF(NOT(ISBLANK(A97)),YEAR(A97),"") -> 2024 | AE97: =IF(NOT(ISBLANK(L97)),YEAR(L97),"") -> 2024 | AF97: =IF(NOT(ISBLANK(L97)),MONTH(L97),"") -> 6
A98: 45461 | B98: 1084 | C98: Patagonia Clima SAS | F98: Placa de Caldera | G98: Peisa | H98: BGL 188 | I98: 153400409 | K98: 45461 | L98: 45476 | M98: 125 | N98: 120000 | O98: Enviado | P98: Reparado | Q98: Aceptado | R98: =IF(Q98="Aceptado",N98,0) -> 120000 | S98: 120000 | T98: =IFERROR(+T97+R98-S98,0) -> 15000 | U98: =IF(NOT(ISBLANK(K98)),MONTH(K98),"") -> 6 | V98: =IF(NOT(ISBLANK(A98)),MONTH(A98),"") -> 6 | W98: =IFERROR(+S98-R98,0) -> 0 | X98: Diego | Z98: 733 | AC98: =IF(NOT(ISBLANK(K98)),YEAR(K98),"") -> 2024 | AD98: =IF(NOT(ISBLANK(A98)),YEAR(A98),"") -> 2024 | AE98: =IF(NOT(ISBLANK(L98)),YEAR(L98),"") -> 2024 | AF98: =IF(NOT(ISBLANK(L98)),MONTH(L98),"") -> 7
A99: 45461 | B99: 1085 | C99: Patagonia Clima SAS | F99: Placa de Caldera | G99: Peisa | H99: BGL 188 | I99: E4XX7 | K99: 45461 | L99: 45476 | M99: 125 | N99: 120000 | O99: Enviado | P99: Reparado | Q99: Aceptado | R99: =IF(Q99="Aceptado",N99,0) -> 120000 | S99: 120000 | T99: =IFERROR(+T98+R99-S99,0) -> 15000 | U99: =IF(NOT(ISBLANK(K99)),MONTH(K99),"") -> 6 | V99: =IF(NOT(ISBLANK(A99)),MONTH(A99),"") -> 6 | W99: =IFERROR(+S99-R99,0) -> 0 | X99: Diego | Z99: 733 | AC99: =IF(NOT(ISBLANK(K99)),YEAR(K99),"") -> 2024 | AD99: =IF(NOT(ISBLANK(A99)),YEAR(A99),"") -> 2024 | AE99: =IF(NOT(ISBLANK(L99)),YEAR(L99),"") -> 2024 | AF99: =IF(NOT(ISBLANK(L99)),MONTH(L99),"") -> 7
A100: 45463 | B100: 1086 | C100: Esteban (Smart 32) | F100: Smart TV 32" | G100: Hitachi | H100: CDH-LE32SMART17 | I100: RF1003413086728 | K100: 45463 | L100: 45466 | M100: 104 | N100: 99500 | O100: Enviado | P100: Reparado | Q100: Aceptado | R100: =IF(Q100="Aceptado",N100,0) -> 99500 | S100: 99500 | T100: =IFERROR(+T99+R100-S100,0) -> 15000 | U100: =IF(NOT(ISBLANK(K100)),MONTH(K100),"") -> 6 | V100: =IF(NOT(ISBLANK(A100)),MONTH(A100),"") -> 6 | W100: =IFERROR(+S100-R100,0) -> 0 | X100: Diego | Z100: 731 | AC100: =IF(NOT(ISBLANK(K100)),YEAR(K100),"") -> 2024 | AD100: =IF(NOT(ISBLANK(A100)),YEAR(A100),"") -> 2024 | AE100: =IF(NOT(ISBLANK(L100)),YEAR(L100),"") -> 2024 | AF100: =IF(NOT(ISBLANK(L100)),MONTH(L100),"") -> 6
...

Sheet Costos Fijos
A1: 2024 | B1: Diego | C1: Laura | D1: Sergio | E1: Camuzzi GAS + Agua | F1: Luz Onelli | G1: Internet | H1: Monotributo + IIBB | I1: Alquiler+exp+Muni | K1: Gastos Var | L1: Total
A2: Enero | B2: 700000 | D2: 700000 | E2: =[1]Enero!$D$8+[1]Enero!$D$10 -> 3400 | F2: =[1]Enero!$D$5 -> 4100 | G2: =[2]Enero!$D$6 -> 0 | H2: 42052.97 | I2: =[1]Enero!$D$7+ [1]Enero!$D$9 -> 1300 | K2: =[1]Enero!$C$58 -> 13729.76 | L2: =SUM(B2:K2) -> 1464582.7
A3: Febrero | B3: 770000 | D3: 770000 | E3: =[1]Febrero!$D$8+[1]Febrero!$D$10 -> 3400 | F3: =[1]Febrero!$D$5 -> 6500 | G3: =[2]Febrero!$D$6 -> 0 | H3: 52019.61 | I3: =[1]Febrero!$D$7+ [1]Febrero!$D$9 -> 218540 | K3: =[1]Febrero!$C$58 -> 162908.07 | L3: =SUM(B3:K3) -> 1983367.7
A4: Marzo | B4: 770000 | D4: 770000 | E4: =[1]Marzo!$D$8+[1]Marzo!$D$10 -> 4200 | F4: =[1]Marzo!$D$5 -> 6500 | G4: =[2]Marzo!$D$6 -> 0 | H4: 52019.61 | I4: =[1]Marzo!$D$7+ [1]Marzo!$D$9 -> 257410 | K4: =[1]Marzo!$C$58 -> 69024.19 | L4: =SUM(B4:K4) -> 1929153.8
A5: Abril | B5: 770000 | D5: 770000 | E5: =[1]Abril!$D$8+[1]Abril!$D$10 -> 4200 | F5: =[1]Abril!$D$5 -> 12350 | G5: =[2]Abril!$D$6 -> 0 | H5: 52019.61 | I5: =[1]Abril!$D$7+ [1]Abril!$D$9 -> 303300 | K5: =[1]Abril!$C$58 -> 31252.73 | L5: =SUM(B5:K5) -> 1943122.3
A6: Mayo | B6: 770000 | D6: 770000 | E6: =[1]Mayo!$D$8+[1]Mayo!$D$10 -> 6300 | F6: =[1]Mayo!$D$5 -> 13215 | G6: =[2]Mayo!$D$6 -> 0 | H6: 52019.61 | I6: =[1]Mayo!$D$7 + [1]Mayo!$D$9 -> 333340 | K6: =[1]Mayo!$C$60 -> 309378.47 | L6: =SUM(B6:K6) -> 2254253.1
A7: Junio | B7: 900000 | D7: 900000 | E7: =[1]Junio!$D$8+[1]Junio!$D$10 -> 6300 | F7: =[1]Junio!$D$5 -> 15000 | G7: =[2]Junio!$D$6 -> 0 | H7: 52019.61 | I7: =[1]Junio!$D$7+ [1]Junio!$D$9 -> 366410 | K7: =[1]Junio!$C$58 -> 195581.23 | L7: =SUM(B7:K7) -> 2435310.8
A8: Julio | B8: 900000 | D8: 900000 | E8: =[1]Julio!$D$8+[1]Julio!$D$10 -> 18100 | F8: =[1]Julio!$D$5 -> 25000 | G8: =[2]Julio!$D$6 -> 0 | H8: 52019.61 | I8: =[1]Julio!$D$7+ [1]Julio!$D$9 -> 402800 | K8: =[1]Julio!$C$58 -> 169177.97 | L8: =SUM(B8:K8) -> 2467097.6
A9: Agosto | B9: 1200000 | D9: 1200000 | E9: =[1]Agosto!$D$8+[1]Agosto!$D$10 -> 18100 | F9: =[1]Agosto!$D$5 -> 27500 | G9: =[2]Agosto!$D$6 -> 0 | H9: 56764.58 | I9: =[1]Agosto!$D$7+ [1]Agosto!$D$9 -> 402800 | K9: =[1]Agosto!$C$58 -> 593043 | L9: =SUM(B9:K9) -> 3498207.6
A10: Septiembre | B10: 1200000 | D10: 1200000 | E10: =[1]Septiembre!$D$8+[1]Septiembre!$D$10 -> 21400 | F10: =[1]Septiembre!$D$5 -> 33000 | G10: =[1]Septiembre!$D$6 -> 0 | H10: 56764.58 | I10: =[1]Septiembre!$D$7 + [1]Septiembre!$D$9 -> 402800 | K10: =[1]Septiembre!$C$58 -> 353258.95 | L10: =SUM(B10:K10) -> 3267223.5
A11: Octubre | B11: 1200000 | D11: 1200000 | E11: =[1]Octubre!$D$8+[1]Octubre!$D$10 -> 21400 | F11: =[1]Octubre!$D$5 -> 33000 | G11: =[1]Octubre!$D$6 -> 12000 | H11: 56764.58 | I11: =[1]Octubre!$D$7 + [1]Octubre!$D$9 -> 402800 | K11: =[1]Octubre!$C$58 -> 304092.08 | L11: =SUM(B11:K11) -> 3230056.7
A12: Noviembre | B12: 1200000 | D12: 1200000 | E12: =[1]Noviembre!$D$8+[1]Noviembre!$D$10 -> 22400 | F12: =[1]Noviembre!$D$5 -> 33000 | G12: =[1]Noviembre!$D$6 -> 12000 | H12: 56764.58 | I12: =[1]Noviembre!$D$7 + [1]Noviembre!$D$9 -> 414806 | K12: =[1]Noviembre!$C$58 -> 264846.26 | L12: =SUM(B12:K12) -> 3203816.8
A13: Diciembre | B13: 1500000 | D13: 1500000 | E13: =[1]Diciembre!$D$8+[1]Diciembre!$D$10 -> 22400 | F13: =[1]Diciembre!$D$5 -> 35000 | G13: =[1]Diciembre!$D$6 -> 12000 | H13: 56764.58 | I13: =[1]Diciembre!$D$7 + [1]Diciembre!$D$9 -> 864470 | K13: =[1]Diciembre!$C$58 -> 55572.73 | L13: =SUM(B13:K13) -> 4046207.3
A14: ANUAL | B14: =SUM(B2:B13) -> 11880000 | C14: =SUM(C2:C13) -> 0 | D14: =SUM(D2:D13) -> 11880000 | E14: =SUM(E2:E13) -> 151600 | F14: =SUM(F2:F13) -> 244165 | G14: =SUM(G2:G13) -> 36000 | H14: =SUM(H2:H13) -> 637993.53 | I14: =SUM(I2:I13) -> 4370776 | ... L14: =SUM(L2:L13) -> 31722400
A18: 2025 | B18: Diego | C18: Laura | D18: Sergio | E18: Camuzzi GAS + Agua | F18: Luz Onelli | G18: Internet | H18: Monotributo + IIBB | I18: Alquiler+exp+Muni | K18: Gastos Var | L18: Total
A19: Enero | B19: 1500000 | D19: 1500000 | E19: =[3]Enero!$D$8+[3]Enero!$D$10 -> 22900 | F19: =[3]Enero!$D$5 -> 36000 | G19: =[3]Enero!$D$6 -> 13500 | H19: 56764.58 | I19: =[3]Enero!$D$7+ [3]Enero!$D$9 -> 2600 | K19: =[3]Enero!$C$58 -> 325599.2 | L19: =SUM(B19:K19) -> 3457363.8
A20: Febrero | B20: 1500000 | D20: 1500000 | E20: =[3]Febrero!$D$8+[3]Febrero!$D$10 -> 22900 | F20: =[3]Febrero!$D$5 -> 36000 | G20: =[3]Febrero!$D$6 -> 13500 | H20: 95327.59 | I20: =[3]Febrero!$D$7+ [3]Febrero!$D$9 -> 449000 | K20: =[3]Febrero!$C$58 -> 79883.81 | L20: =SUM(B20:K20) -> 3696611.4
A21: Marzo | B21: 1500000 | D21: 1500000 | E21: =[3]Marzo!$D$8+[3]Marzo!$D$10 -> 19400 | F21: =[3]Marzo!$D$5 -> 39500 | G21: =[3]Marzo!$D$6 -> 13500 | H21: 95327.59 | I21: =[3]Marzo!$D$7+ [3]Marzo!$D$9 -> 456000 | K21: =[3]Marzo!$C$58 -> 84314.89 | L21: =SUM(B21:K21) -> 3708042.5
A22: Abril | B22: 1500000 | D22: 1500000 | E22: =[3]Abril!$D$8+[3]Abril!$D$10 -> 19400 | F22: =[3]Abril!$D$5 -> 39500 | G22: =[3]Abril!$D$6 -> 14800 | H22: 95327.59 | I22: =[3]Abril!$D$7+ [3]Abril!$D$9 -> 463000 | K22: =[3]Abril!$C$58 -> 207786.97 | L22: =SUM(B22:K22) -> 3839814.6
A23: Mayo | B23: 1800000 | D23: 1800000 | E23: =[3]Mayo!$D$8+[3]Mayo!$D$10 -> 23200 | F23: =[3]Mayo!$D$5 -> 39500 | G23: =[3]Mayo!$D$6 -> 14800 | H23: 95327.59 | I23: =[3]Mayo!$D$7 + [3]Mayo!$D$9 -> 475000 | K23: =[3]Mayo!$C$58 -> 1290232.6 | L23: =SUM(B23:K23) -> 5538060.2
A24: Junio | B24: 1800000 | D24: 1800000 | E24: =[3]Junio!$D$8+[3]Junio!$D$10 -> 23200 | F24: =[3]Junio!$D$5 -> 43500 | G24: =[3]Junio!$D$6 -> 14800 | H24: 95327.59 | I24: =[3]Junio!$D$7+ [3]Junio!$D$9 -> 487000 | K24: =[3]Junio!$C$58 -> 195884.94 | L24: =SUM(B24:K24) -> 4459712.5
A25: Julio | B25: 1800000 | D25: 1800000 | E25: =[3]Julio!$D$8+[3]Julio!$D$10 -> 29500 | F25: =[3]Julio!$D$5 -> 48900 | G25: =[3]Julio!$D$6 -> 16300 | H25: 95327.59 | I25: =[3]Julio!$D$7+ [3]Julio!$D$9 -> 500000 | K25: =[3]Julio!$C$58 -> 134695.82 | L25: =SUM(B25:K25) -> 4424723.4
A26: Agosto | B26: 1800000 | D26: 1800000 | E26: =[3]Agosto!$D$8+[3]Agosto!$D$10 -> 29500 | F26: =[3]Agosto!$D$5 -> 54200 | G26: =[3]Agosto!$D$6 -> 16300 | H26: 189982.51 | I26: =[3]Agosto!$D$7+ [3]Agosto!$D$9 -> 508000 | K26: =[3]Agosto!$C$58 -> 151601.85 | L26: =SUM(B26:K26) -> 4549584.4
A27: Septiembre | B27: 1800000 | D27: 1799999.5 | E27: =[3]Septiembre!$D$8+[3]Septiembre!$D$10 -> 0 | F27: =[3]Septiembre!$D$5 -> 0 | G27: =[3]Septiembre!$D$6 -> 105000 | H27: 189982.51 | I27: =[3]Septiembre!$D$7 + [3]Septiembre!$D$9 -> 511000 | K27: =[3]Septiembre!$C$58 -> 335692.64 | L27: =SUM(B27:K27) -> 4741674.6
A28: Octubre | B28: 1999999.6 | D28: 2000000 | E28: =[3]Octubre!$D$8+[3]Octubre!$D$10 -> 36000 | F28: =[3]Octubre!$D$5 -> 54200 | G28: =[3]Octubre!$D$6 -> 16300 | H28: 189982.51 | I28: =[3]Octubre!$D$7 + [3]Octubre!$D$9 -> 524000 | K28: =[3]Octubre!$C$58 -> 936672.5 | L28: =SUM(B28:K28) -> 5757154.6
A29: Noviembre | B29: 2000000 | D29: 2000000 | E29: =[3]Noviembre!$D$8+[3]Noviembre!$D$10 -> 36000 | F29: =[3]Noviembre!$D$5 -> 54200 | G29: =[3]Noviembre!$D$6 -> 18800 | H29: 379965.02 | I29: =[3]Noviembre!$D$7 + [3]Noviembre!$D$9 -> 535000 | K29: =[3]Noviembre!$C$58 -> 134135.39 | L29: =SUM(B29:K29) -> 5158100.4
A30: Diciembre | B30: 2000000 | D30: 303890 | E30: =[3]Diciembre!$D$8+[3]Diciembre!$D$10 -> 36000 | F30: =[3]Diciembre!$D$5 -> 54200 | G30: =[3]Diciembre!$D$6 -> 18800 | H30: 189982.51 | I30: =[3]Diciembre!$D$7 + [3]Diciembre!$D$9 -> 1098000 | K30: =[3]Diciembre!$C$58 -> 110650.39 | L30: =SUM(B30:K30) -> 3811522.9
A31: ANUAL | B31: =SUM(B19:B30) -> 21000000 | C31: =SUM(C19:C30) -> 0 | D31: =SUM(D19:D30) -> 19303890 | E31: =SUM(E19:E30) -> 298000 | F31: =SUM(F19:F30) -> 499700 | G31: =SUM(G19:G30) -> 276400 | H31: =SUM(H19:H30) -> 1768625.2 | I31: =SUM(I19:I30) -> 6008600 | ... L31: =SUM(L19:L30) -> 53142365
A35: 2026 | B35: Diego | C35: Laura | D35: Sergio | E35: Camuzzi GAS + Agua | F35: Luz Onelli | G35: Internet | H35: Monotributo + IIBB | I35: Alquiler+exp+Muni | K35: Gastos Var | L35: Total
A36: Enero | B36: 2000000 | E36: =[4]Enero!$D$8+[4]Enero!$D$10 -> 36000 | F36: =[4]Enero!$D$5 -> 54200 | G36: =[4]Enero!$D$6 -> 18800 | H36: 189982.51 | I36: =[4]Enero!$D$7+ [4]Enero!$D$9 -> 5000 | K36: =[4]Enero!$C$58 -> 211964.57 | L36: =SUM(B36:K36) -> 2515947.1
A37: Febrero | B37: 2000000 | E37: =[4]Febrero!$D$8+[4]Febrero!$D$10 -> 36000 | F37: =[4]Febrero!$D$5 -> 54200 | G37: =[4]Febrero!$D$6 -> 18800 | H37: 217143.1 | I37: =[4]Febrero!$D$7+ [4]Febrero!$D$9 -> 573000 | K37: =[4]Febrero!$C$58 -> 213976.92 | L37: =SUM(B37:K37) -> 3113120
A38: Marzo | B38: 2000000 | E38: =[4]Marzo!$D$8+[4]Marzo!$D$10 -> 36600 | F38: =[4]Marzo!$D$5 -> 54200 | G38: =[4]Marzo!$D$6 -> 19700 | H38: 217143.1 | I38: =[4]Marzo!$D$7+ [4]Marzo!$D$9 -> 583000 | K38: =[4]Marzo!$C$58 -> 308946.09 | L38: =SUM(B38:K38) -> 3219589.2
A39: Abril | B39: 2000000 | E39: =[4]Abril!$D$8+[4]Abril!$D$10 -> 36600 | F39: =[4]Abril!$D$5 -> 54200 | G39: =[4]Abril!$D$6 -> 19700 | H39: 217143.1 | I39: =[4]Abril!$D$7+ [4]Abril!$D$9 -> 595000 | K39: =[4]Abril!$C$58 -> 352889.32 | L39: =SUM(B39:K39) -> 3275532.4
A40: Mayo | E40: =[4]Mayo!$D$8+[4]Mayo!$D$10 -> 0 | F40: =[4]Mayo!$D$5 -> 0 | G40: =[4]Mayo!$D$6 -> 0 | I40: =[4]Mayo!$D$7 + [4]Mayo!$D$9 -> 0 | K40: =[4]Mayo!$C$58 -> 0 | L40: =SUM(B40:K40) -> 0
A41: Junio | E41: =[4]Junio!$D$8+[4]Junio!$D$10 -> 0 | F41: =[4]Junio!$D$5 -> 0 | G41: =[4]Junio!$D$6 -> 0 | I41: =[4]Junio!$D$7+ [4]Junio!$D$9 -> 0 | K41: =[4]Junio!$C$58 -> 0 | L41: =SUM(B41:K41) -> 0
A42: Julio | E42: =[4]Julio!$D$8+[4]Julio!$D$10 -> 0 | F42: =[4]Julio!$D$5 -> 0 | G42: =[4]Julio!$D$6 -> 0 | I42: =[4]Julio!$D$7+ [4]Julio!$D$9 -> 0 | K42: =[4]Julio!$C$58 -> 0 | L42: =SUM(B42:K42) -> 0
A43: Agosto | E43: =[4]Agosto!$D$8+[4]Agosto!$D$10 -> 0 | F43: =[4]Agosto!$D$5 -> 0 | G43: =[4]Agosto!$D$6 -> 0 | I43: =[4]Agosto!$D$7+ [4]Agosto!$D$9 -> 0 | K43: =[4]Agosto!$C$58 -> 0 | L43: =SUM(B43:K43) -> 0
A44: Septiembre | E44: =[3]Septiembre!$D$8+[3]Septiembre!$D$10 -> 0 | F44: =[4]Septiembre!$D$5 -> 0 | G44: =[4]Septiembre!$D$6 -> 0 | I44: =[4]Septiembre!$D$7 + [4]Septiembre!$D$9 -> 0 | K44: =[4]Septiembre!$C$58 -> 0 | L44: =SUM(B44:K44) -> 0
A45: Octubre | E45: =[4]Octubre!$D$8+[4]Octubre!$D$10 -> 0 | F45: =[4]Octubre!$D$5 -> 0 | G45: =[4]Octubre!$D$6 -> 0 | I45: =[4]Octubre!$D$7 + [4]Octubre!$D$9 -> 0 | K45: =[4]Octubre!$C$58 -> 0 | L45: =SUM(B45:K45) -> 0
A46: Noviembre | E46: =[4]Noviembre!$D$8+[4]Noviembre!$D$10 -> 0 | F46: =[4]Noviembre!$D$5 -> 0 | G46: =[4]Noviembre!$D$6 -> 0 | I46: =[4]Noviembre!$D$7 + [4]Noviembre!$D$9 -> 0 | K46: =[4]Noviembre!$C$58 -> 0 | L46: =SUM(B46:K46) -> 0
A47: Diciembre | E47: =[4]Diciembre!$D$8+[4]Diciembre!$D$10 -> 0 | F47: =[4]Diciembre!$D$5 -> 0 | G47: =[4]Diciembre!$D$6 -> 0 | I47: =[4]Diciembre!$D$7 + [4]Diciembre!$D$9 -> 0 | K47: =[4]Diciembre!$C$58 -> 0 | L47: =SUM(B47:K47) -> 0
A48: ANUAL | B48: =SUM(B36:B47) -> 8000000 | C48: =SUM(C36:C47) -> 0 | D48: =SUM(D36:D47) -> 0 | E48: =SUM(E36:E47) -> 145200 | F48: =SUM(F36:F47) -> 216800 | G48: =SUM(G36:G47) -> 77000 | H48: =SUM(H36:H47) -> 841411.81 | I48: =SUM(I36:I47) -> 1756000 | ... L48: =SUM(L36:L47) -> 12124189

Sheet Resumen
A1: 2024 | B1: Facturacion | C1: Ganacia neta | D1: % costos fijos | E1: Cant Rep | F1: Cant Ent | G1: Dif GB-Fact | H1: Ganancia ELS | I1: Utilidad neta | J1: A COBRAR | K1: INVERTIDO | L1: INGRESO POR INVERSIÓN | M1: DÓLARES | O1: CAJA AÑO ANTERIOR | P1: -104012
A2: Enero | B2: =SUMIFS(Ordenes!R$2:R$1493,Ordenes!AF$2:AF$1493,MONTH(A2 &1),Ordenes!AE$2:AE$1493,A$1) -> 874050 | C2: =+B2-'Costos Fijos'!L2 -> -590532.73 | D2: =IFERROR(1-(C2/B2),"") -> 1.6756281 | E2: =COUNTIFS(Ordenes!U:U,MONTH(A2 &1),Ordenes!AC:AC,A$1) -> 16 | F2: =COUNTIFS(Ordenes!V:V,MONTH(A2 &1),Ordenes!AD:AD,A$1) -> 18 | G2: =B2-C2 -> 1464582.7 | H2: =+C2 -> -590532.73 | I2: =IFERROR(+H2/B2,"") -> -0.67562809 | J2: =-SUMIFS(Ordenes!W$2:W$1493,Ordenes!AF$2:AF$1493,MONTH(A2 &1),Ordenes!AE$2:AE$1493,A$1) -> 0 | L2: =891130+83253.6 -> 974383.6
A3: Febrero | B3: =SUMIFS(Ordenes!R$2:R$1493,Ordenes!AF$2:AF$1493,MONTH(A3 &1),Ordenes!AE$2:AE$1493,A$1) -> 3505517 | C3: =+B3-'Costos Fijos'!L3 -> 1522149.3 | D3: =IFERROR(1-(C3/B3),"") -> 0.56578464 | E3: =COUNTIFS(Ordenes!U:U,MONTH(A3 &1),Ordenes!AC:AC,A$1) -> 15 | F3: =COUNTIFS(Ordenes!V:V,MONTH(A3 &1),Ordenes!AD:AD,A$1) -> 15 | G3: =B3-C3 -> 1983367.7 | H3: =+C3 -> 1522149.3 | I3: =IFERROR(+H3/B3,"") -> 0.43421536 | J3: =-SUMIFS(Ordenes!W$2:W$1493,Ordenes!AF$2:AF$1493,MONTH(A3 &1),Ordenes!AE$2:AE$1493,A$1) -> 0 | K3: =800000+1000000+310500 -> 2110500 | L3: =680594.32+61533.19+459512+41544.96 -> 1243184.5 | M3: 300
A4: Marzo | B4: =SUMIFS(Ordenes!R$2:R$1493,Ordenes!AF$2:AF$1493,MONTH(A4 &1),Ordenes!AE$2:AE$1493,A$1) -> 1307235 | C4: =+B4-'Costos Fijos'!L4 -> -621918.8 | D4: =IFERROR(1-(C4/B4),"") -> 1.4757513 | E4: =COUNTIFS(Ordenes!U:U,MONTH(A4 &1),Ordenes!AC:AC,A$1) -> 15 | F4: =COUNTIFS(Ordenes!V:V,MONTH(A4 &1),Ordenes!AD:AD,A$1) -> 15 | G4: =B4-C4 -> 1929153.8 | H4: =+C4 -> -621918.8 | I4: =IFERROR(+H4/B4,"") -> -0.47575134 | J4: =-SUMIFS(Ordenes!W$2:W$1493,Ordenes!AF$2:AF$1493,MONTH(A4 &1),Ordenes!AE$2:AE$1493,A$1) -> 0 | L4: =847344.52+153218.46+988365.6+178718.16 -> 2167646.7
A5: Abril | B5: =SUMIFS(Ordenes!R$2:R$1493,Ordenes!AF$2:AF$1493,MONTH(A5 &1),Ordenes!AE$2:AE$1493,A$1) -> 1606700 | C5: =+B5-'Costos Fijos'!L5 -> -336422.34 | D5: =IFERROR(1-(C5/B5),"") -> 1.2093872 | E5: =COUNTIFS(Ordenes!U:U,MONTH(A5 &1),Ordenes!AC:AC,A$1) -> 12 | F5: =COUNTIFS(Ordenes!V:V,MONTH(A5 &1),Ordenes!AD:AD,A$1) -> 12 | G5: =B5-C5 -> 1943122.3 | H5: =+C5 -> -336422.34 | I5: =IFERROR(+H5/B5,"") -> -0.20938715 | J5: =-SUMIFS(Ordenes!W$2:W$1493,Ordenes!AF$2:AF$1493,MONTH(A5 &1),Ordenes!AE$2:AE$1493,A$1) -> 0 | K5: =1500000+1000000+1008557.89 -> 3508557.9 | L5: =405193.19 +112343.97+190.61+1500000+86301 -> 2104028.8
A6: Mayo | B6: =SUMIFS(Ordenes!R$2:R$1493,Ordenes!AF$2:AF$1493,MONTH(A6 &1),Ordenes!AE$2:AE$1493,A$1) -> 3641029 | C6: =+B6-'Costos Fijos'!L6 -> 1386775.9 | D6: =IFERROR(1-(C6/B6),"") -> 0.61912527 | E6: =COUNTIFS(Ordenes!U:U,MONTH(A6 &1),Ordenes!AC:AC,A$1) -> 23 | F6: =COUNTIFS(Ordenes!V:V,MONTH(A6 &1),Ordenes!AD:AD,A$1) -> 24 | G6: =B6-C6 -> 2254253.1 | H6: =+C6 -> 1386775.9 | I6: =IFERROR(+H6/B6,"") -> 0.38087473 | J6: =-SUMIFS(Ordenes!W$2:W$1493,Ordenes!AF$2:AF$1493,MONTH(A6 &1),Ordenes!AE$2:AE$1493,A$1) -> 0 | K6: 520000 | M6: 500
A7: Junio | B7: =SUMIFS(Ordenes!R$2:R$1493,Ordenes!AF$2:AF$1493,MONTH(A7 &1),Ordenes!AE$2:AE$1493,A$1) -> 3587405 | C7: =+B7-'Costos Fijos'!L7 -> 1152094.2 | D7: =IFERROR(1-(C7/B7),"") -> 0.67885027 | E7: =COUNTIFS(Ordenes!U:U,MONTH(A7 &1),Ordenes!AC:AC,A$1) -> 19 | F7: =COUNTIFS(Ordenes!V:V,MONTH(A7 &1),Ordenes!AD:AD,A$1) -> 21 | G7: =B7-C7 -> 2435310.8 | H7: =+C7 -> 1152094.2 | I7: =IFERROR(+H7/B7,"") -> 0.32114973 | J7: =-SUMIFS(Ordenes!W$2:W$1493,Ordenes!AF$2:AF$1493,MONTH(A7 &1),Ordenes!AE$2:AE$1493,A$1) -> 15000 | K7: 1512789.6
A8: Julio | B8: =SUMIFS(Ordenes!R$2:R$1493,Ordenes!AF$2:AF$1493,MONTH(A8 &1),Ordenes!AE$2:AE$1493,A$1) -> 3048355 | C8: =+B8-'Costos Fijos'!L8 -> 581257.42 | D8: =IFERROR(1-(C8/B8),"") -> 0.80932096 | E8: =COUNTIFS(Ordenes!U:U,MONTH(A8 &1),Ordenes!AC:AC,A$1) -> 16 | F8: =COUNTIFS(Ordenes!V:V,MONTH(A8 &1),Ordenes!AD:AD,A$1) -> 20 | G8: =B8-C8 -> 2467097.6 | H8: =+C8 -> 581257.42 | I8: =IFERROR(+H8/B8,"") -> 0.19067904 | J8: =-SUMIFS(Ordenes!W$2:W$1493,Ordenes!AF$2:AF$1493,MONTH(A8 &1),Ordenes!AE$2:AE$1493,A$1) -> 0
A9: Agosto | B9: =SUMIFS(Ordenes!R$2:R$1493,Ordenes!AF$2:AF$1493,MONTH(A9 &1),Ordenes!AE$2:AE$1493,A$1) -> 4608450 | C9: =+B9-'Costos Fijos'!L9 -> 1110242.4 | D9: =IFERROR(1-(C9/B9),"") -> 0.7590855 | E9: =COUNTIFS(Ordenes!U:U,MONTH(A9 &1),Ordenes!AC:AC,A$1) -> 14 | F9: =COUNTIFS(Ordenes!V:V,MONTH(A9 &1),Ordenes!AD:AD,A$1) -> 9 | G9: =B9-C9 -> 3498207.6 | H9: =+C9 -> 1110242.4 | I9: =IFERROR(+H9/B9,"") -> 0.2409145 | J9: =-SUMIFS(Ordenes!W$2:W$1493,Ordenes!AF$2:AF$1493,MONTH(A9 &1),Ordenes!AE$2:AE$1493,A$1) -> 0 | K9: =1614344.15+408000 -> 2022344.1 | M9: 300
A10: Septiembre | B10: =SUMIFS(Ordenes!R$2:R$1493,Ordenes!AF$2:AF$1493,MONTH(A10 &1),Ordenes!AE$2:AE$1493,A$1)+20000 -> 4334881 | C10: =+B10-'Costos Fijos'!L10 -> 1067657.5 | D10: =IFERROR(1-(C10/B10),"") -> 0.75370547 | E10: =COUNTIFS(Ordenes!U:U,MONTH(A10 &1),Ordenes!AC:AC,A$1) -> 23 | F10: =COUNTIFS(Ordenes!V:V,MONTH(A10 &1),Ordenes!AD:AD,A$1) -> 25 | G10: =B10-C10 -> 3267223.5 | H10: =+C10 -> 1067657.5 | I10: =IFERROR(+H10/B10,"") -> 0.24629453 | J10: =-SUMIFS(Ordenes!W$2:W$1493,Ordenes!AF$2:AF$1493,MONTH(A10 &1),Ordenes!AE$2:AE$1493,A$1) -> 0
A11: Octubre | B11: =SUMIFS(Ordenes!R$2:R$1493,Ordenes!AF$2:AF$1493,MONTH(A11 &1),Ordenes!AE$2:AE$1493,A$1) -> 2852200 | C11: =+B11-'Costos Fijos'!L11 -> -377856.66 | D11: =IFERROR(1-(C11/B11),"") -> 1.132479 | E11: =COUNTIFS(Ordenes!U:U,MONTH(A11 &1),Ordenes!AC:AC,A$1) -> 16 | F11: =COUNTIFS(Ordenes!V:V,MONTH(A11 &1),Ordenes!AD:AD,A$1) -> 14 | G11: =B11-C11 -> 3230056.7 | H11: =+C11 -> -377856.66 | I11: =IFERROR(+H11/B11,"") -> -0.13247902 | J11: =-SUMIFS(Ordenes!W$2:W$1493,Ordenes!AF$2:AF$1493,MONTH(A11 &1),Ordenes!AE$2:AE$1493,A$1) -> 0 | K11: =367500+610000+1714771.39 -> 2692271.4 | M11: =300+500 -> 800 | P11: =P1+H14-J14 -> 3448170
A12: Noviembre | B12: =SUMIFS(Ordenes!R$2:R$1493,Ordenes!AF$2:AF$1493,MONTH(A12 &1),Ordenes!AE$2:AE$1493,A$1) -> 3754660 | C12: =+B12-'Costos Fijos'!L12 -> 550843.16 | D12: =IFERROR(1-(C12/B12),"") -> 0.8532908 | E12: =COUNTIFS(Ordenes!U:U,MONTH(A12 &1),Ordenes!AC:AC,A$1) -> 20 | F12: =COUNTIFS(Ordenes!V:V,MONTH(A12 &1),Ordenes!AD:AD,A$1) -> 22 | G12: =B12-C12 -> 3203816.8 | H12: =+C12 -> 550843.16 | I12: =IFERROR(+H12/B12,"") -> 0.1467092 | J12: =-SUMIFS(Ordenes!W$2:W$1493,Ordenes!AF$2:AF$1493,MONTH(A12 &1),Ordenes!AE$2:AE$1493,A$1) -> 0 | M12: 1450.03 | O12: EQUIPOS 2023 COBRADOS EN 2024
A13: Diciembre | B13: =SUMIFS(Ordenes!R$2:R$1493,Ordenes!AF$2:AF$1493,MONTH(A13 &1),Ordenes!AE$2:AE$1493,A$1) -> 2169100 | C13: =+B13-'Costos Fijos'!L13 -> -1877107.3 | D13: =IFERROR(1-(C13/B13),"") -> 1.8653853 | E13: =COUNTIFS(Ordenes!U:U,MONTH(A13 &1),Ordenes!AC:AC,A$1) -> 12 | F13: =COUNTIFS(Ordenes!V:V,MONTH(A13 &1),Ordenes!AD:AD,A$1) -> 12 | G13: =B13-C13 -> 4046207.3 | H13: =+C13 -> -1877107.3 | I13: =IFERROR(+H13/B13,"") -> -0.86538533 | J13: =-SUMIFS(Ordenes!W$2:W$1493,Ordenes!AF$2:AF$1493,MONTH(A13 &1),Ordenes!AE$2:AE$1493,A$1) -> 0 | K13: 602500 | M13: 500 | O13: TOTAL REAL EN CAJA | P13: =P11+P12+L14-K14 -> -3031549.5 | Q13: Negativo por el desfasaje de retiro de sueldo de 2024 en 2025
A14: ANUAL | B14: =SUM(B2:B13) -> 35289582 | C14: =SUM(C2:C13) -> 3567182 | D14: =IFERROR(1-(C14/B14),"") -> 0.89891685 | E14: =SUM(E2:E13) -> 201 | F14: =SUM(F2:F13) -> 207 | G14: =B14-C14 -> 31722400 | H14: =+C14 -> 3567182 | I14: =IFERROR(+H14/B14,"") -> 0.10108315 | J14: =SUM(J2:J13) -> 15000 | K14: =SUM(K2:K13) -> 12968963 | L14: =SUM(L2:L13) -> 6489243.6 | M14: =SUM(M2:M13)+2239 -> 6089.03 | O14: DIEFERENCIA CON CAJA BRC | P14: =P13-'[5]2024'!$P$500 -> 0.49
A17: 2025 | B17: Facturacion | C17: Ganacia neta | D17: % costos fijos | E17: Cant Rep | F17: Cant Ent | G17: Dif GB-Fact | H17: Ganancia ELS | I17: Utilidad neta | J17: A COBRAR | K17: INVERTIDO | L17: INGRESO POR INVERSIÓN | M17: DÓLARES
A18: Enero | B18: =SUMIFS(Ordenes!R$2:R$1493,Ordenes!AF$2:AF$1493,MONTH(A18 &1),Ordenes!AE$2:AE$1493,A$17) -> 3238880 | C18: =+B18-'Costos Fijos'!L19 -> -218483.78 | D18: =IFERROR(1-(C18/B18),"") -> 1.0674566 | E18: =COUNTIFS(Ordenes!U:U,MONTH(A18 &17),Ordenes!AC:AC,A$17) -> 20 | F18: =COUNTIFS(Ordenes!V:V,MONTH(A18 &17),Ordenes!AD:AD,A$17) -> 23 | G18: =B18-C18 -> 3457363.8 | H18: =+C18 -> -218483.78 | I18: =IFERROR(+H18/B18,"") -> -0.067456584 | J18: =-SUMIFS(Ordenes!W$2:W$1493,Ordenes!AF$2:AF$1493,MONTH(A18 &17),Ordenes!AE$2:AE$1493,A$17) -> 0 | L18: 400661.78
A19: Febrero | B19: =SUMIFS(Ordenes!R$2:R$1493,Ordenes!AF$2:AF$1493,MONTH(A19 &1),Ordenes!AE$2:AE$1493,A$17) -> 4778900 | C19: =+B19-'Costos Fijos'!L20 -> 1082288.6 | D19: =IFERROR(1-(C19/B19),"") -> 0.77352767 | E19: =COUNTIFS(Ordenes!U:U,MONTH(A19 &17),Ordenes!AC:AC,A$17) -> 22 | F19: =COUNTIFS(Ordenes!V:V,MONTH(A19 &17),Ordenes!AD:AD,A$17) -> 21 | G19: =B19-C19 -> 3696611.4 | H19: =+C19 -> 1082288.6 | I19: =IFERROR(+H19/B19,"") -> 0.22647233 | J19: =-SUMIFS(Ordenes!W$2:W$1493,Ordenes!AF$2:AF$1493,MONTH(A19 &17),Ordenes!AE$2:AE$1493,A$17) -> 0 | L19: 702120.45
A20: Marzo | B20: =SUMIFS(Ordenes!R$2:R$1493,Ordenes!AF$2:AF$1493,MONTH(A20 &1),Ordenes!AE$2:AE$1493,A$17) -> 3145000 | C20: =+B20-'Costos Fijos'!L21 -> -563042.48 | D20: =IFERROR(1-(C20/B20),"") -> 1.1790278 | E20: =COUNTIFS(Ordenes!U:U,MONTH(A20 &17),Ordenes!AC:AC,A$17) -> 19 | F20: =COUNTIFS(Ordenes!V:V,MONTH(A20 &17),Ordenes!AD:AD,A$17) -> 16 | G20: =B20-C20 -> 3708042.5 | H20: =+C20 -> -563042.48 | I20: =IFERROR(+H20/B20,"") -> -0.17902782 | J20: =-SUMIFS(Ordenes!W$2:W$1493,Ordenes!AF$2:AF$1493,MONTH(A20 &17),Ordenes!AE$2:AE$1493,A$17) -> 0 | L20: 799548.96
A21: Abril | B21: =SUMIFS(Ordenes!R$2:R$1493,Ordenes!AF$2:AF$1493,MONTH(A21 &1),Ordenes!AE$2:AE$1493,A$17) -> 5599600 | C21: =+B21-'Costos Fijos'!L22 -> 1759785.4 | D21: =IFERROR(1-(C21/B21),"") -> 0.68573015 | E21: =COUNTIFS(Ordenes!U:U,MONTH(A21 &17),Ordenes!AC:AC,A$17) -> 23 | F21: =COUNTIFS(Ordenes!V:V,MONTH(A21 &17),Ordenes!AD:AD,A$17) -> 23 | G21: =B21-C21 -> 3839814.6 | H21: =+C21 -> 1759785.4 | I21: =IFERROR(+H21/B21,"") -> 0.31426985 | J21: =-SUMIFS(Ordenes!W$2:W$1493,Ordenes!AF$2:AF$1493,MONTH(A21 &17),Ordenes!AE$2:AE$1493,A$17) -> 0 | K21: 1842500 | L21: 708435.94 | M21: 1500
A22: Mayo | B22: =SUMIFS(Ordenes!R$2:R$1493,Ordenes!AF$2:AF$1493,MONTH(A22 &1),Ordenes!AE$2:AE$1493,A$17) -> 4027500 | C22: =+B22-'Costos Fijos'!L23 -> -1510560.2 | D22: =IFERROR(1-(C22/B22),"") -> 1.3750615 | E22: =COUNTIFS(Ordenes!U:U,MONTH(A22 &17),Ordenes!AC:AC,A$17) -> 15 | F22: =COUNTIFS(Ordenes!V:V,MONTH(A22 &17),Ordenes!AD:AD,A$17) -> 21 | G22: =B22-C22 -> 5538060.2 | H22: =+C22 -> -1510560.2 | I22: =IFERROR(+H22/B22,"") -> -0.37506151 | J22: =-SUMIFS(Ordenes!W$2:W$1493,Ordenes!AF$2:AF$1493,MONTH(A22 &17),Ordenes!AE$2:AE$1493,A$17) -> 172500 | L22: 4613587.4
A23: Junio | B23: =SUMIFS(Ordenes!R$2:R$1493,Ordenes!AF$2:AF$1493,MONTH(A23 &1),Ordenes!AE$2:AE$1493,A$17) -> 4182750 | C23: =+B23-'Costos Fijos'!L24 -> -276962.53 | D23: =IFERROR(1-(C23/B23),"") -> 1.0662154 | E23: =COUNTIFS(Ordenes!U:U,MONTH(A23 &17),Ordenes!AC:AC,A$17) -> 23 | F23: =COUNTIFS(Ordenes!V:V,MONTH(A23 &17),Ordenes!AD:AD,A$17) -> 24 | G23: =B23-C23 -> 4459712.5 | H23: =+C23 -> -276962.53 | I23: =IFERROR(+H23/B23,"") -> -0.066215416 | J23: =-SUMIFS(Ordenes!W$2:W$1493,Ordenes!AF$2:AF$1493,MONTH(A23 &17),Ordenes!AE$2:AE$1493,A$17) -> 0 | L23: 899868.1
A24: Julio | B24: =SUMIFS(Ordenes!R$2:R$1493,Ordenes!AF$2:AF$1493,MONTH(A24 &1),Ordenes!AE$2:AE$1493,A$17) -> 4337105 | C24: =+B24-'Costos Fijos'!L25 -> -87618.41 | D24: =IFERROR(1-(C24/B24),"") -> 1.020202 | E24: =COUNTIFS(Ordenes!U:U,MONTH(A24 &17),Ordenes!AC:AC,A$17) -> 21 | F24: =COUNTIFS(Ordenes!V:V,MONTH(A24 &17),Ordenes!AD:AD,A$17) -> 19 | G24: =B24-C24 -> 4424723.4 | H24: =+C24 -> -87618.41 | I24: =IFERROR(+H24/B24,"") -> -0.02020205 | J24: =-SUMIFS(Ordenes!W$2:W$1493,Ordenes!AF$2:AF$1493,MONTH(A24 &17),Ordenes!AE$2:AE$1493,A$17) -> 0
A25: Agosto | B25: =SUMIFS(Ordenes!R$2:R$1493,Ordenes!AF$2:AF$1493,MONTH(A25 &1),Ordenes!AE$2:AE$1493,A$17) -> 7692675 | C25: =+B25-'Costos Fijos'!L26 -> 3143090.6 | D25: =IFERROR(1-(C25/B25),"") -> 0.59141773 | E25: =COUNTIFS(Ordenes!U:U,MONTH(A25 &17),Ordenes!AC:AC,A$17) -> 15 | F25: =COUNTIFS(Ordenes!V:V,MONTH(A25 &17),Ordenes!AD:AD,A$17) -> 15 | G25: =B25-C25 -> 4549584.4 | H25: =+C25 -> 3143090.6 | I25: =IFERROR(+H25/B25,"") -> 0.40858227 | J25: =-SUMIFS(Ordenes!W$2:W$1493,Ordenes!AF$2:AF$1493,MONTH(A25 &17),Ordenes!AE$2:AE$1493,A$17) -> 0 | K25: 3680000 | L25: 902009.81 | M25: 2000
A26: Septiembre | B26: =SUMIFS(Ordenes!R$2:R$1493,Ordenes!AF$2:AF$1493,MONTH(A26 &1),Ordenes!AE$2:AE$1493,A$17) -> 7303641 | C26: =+B26-'Costos Fijos'!L27 -> 2561966.4 | D26: =IFERROR(1-(C26/B26),"") -> 0.64922066 | E26: =COUNTIFS(Ordenes!U:U,MONTH(A26 &17),Ordenes!AC:AC,A$17) -> 17 | F26: =COUNTIFS(Ordenes!V:V,MONTH(A26 &17),Ordenes!AD:AD,A$17) -> 17 | G26: =B26-C26 -> 4741674.6 | H26: =+C26 -> 2561966.4 | I26: =IFERROR(+H26/B26,"") -> 0.35077934 | J26: =-SUMIFS(Ordenes!W$2:W$1493,Ordenes!AF$2:AF$1493,MONTH(A26 &17),Ordenes!AE$2:AE$1493,A$17) -> 0 | K26: 2000000 | L26: 2150546
A27: Octubre | B27: =SUMIFS(Ordenes!R$2:R$1493,Ordenes!AF$2:AF$1493,MONTH(A27 &1),Ordenes!AE$2:AE$1493,A$17) -> 7673450 | C27: =+B27-'Costos Fijos'!L28 -> 1916295.4 | D27: =IFERROR(1-(C27/B27),"") -> 0.75026939 | E27: =COUNTIFS(Ordenes!U:U,MONTH(A27 &17),Ordenes!AC:AC,A$17) -> 22 | F27: =COUNTIFS(Ordenes!V:V,MONTH(A27 &17),Ordenes!AD:AD,A$17) -> 21 | G27: =B27-C27 -> 5757154.6 | H27: =+C27 -> 1916295.4 | I27: =IFERROR(+H27/B27,"") -> 0.24973061 | J27: =-SUMIFS(Ordenes!W$2:W$1493,Ordenes!AF$2:AF$1493,MONTH(A27 &17),Ordenes!AE$2:AE$1493,A$17) -> 0 | K27: 2760000 | L27: 2028420.9 | M27: 500 | P27: =P13+H30-J30 -> 2729086.2
A28: Noviembre | B28: =SUMIFS(Ordenes!R$2:R$1493,Ordenes!AF$2:AF$1493,MONTH(A28 &1),Ordenes!AE$2:AE$1493,A$17) -> 4904000 | C28: =+B28-'Costos Fijos'!L29 -> -254100.41 | D28: =IFERROR(1-(C28/B28),"") -> 1.0518149 | E28: =COUNTIFS(Ordenes!U:U,MONTH(A28 &17),Ordenes!AC:AC,A$17) -> 18 | F28: =COUNTIFS(Ordenes!V:V,MONTH(A28 &17),Ordenes!AD:AD,A$17) -> 11 | G28: =B28-C28 -> 5158100.4 | H28: =+C28 -> -254100.41 | I28: =IFERROR(+H28/B28,"") -> -0.051814929 | J28: =-SUMIFS(Ordenes!W$2:W$1493,Ordenes!AF$2:AF$1493,MONTH(A28 &17),Ordenes!AE$2:AE$1493,A$17) -> 0 | K28: 999882.21 | L28: 2713698.2 | O28: EQUIPOS 2024 COBRADOS EN 2025
A29: Diciembre | B29: =SUMIFS(Ordenes!R$2:R$1493,Ordenes!AF$2:AF$1493,MONTH(A29 &1),Ordenes!AE$2:AE$1493,A$17) -> 2192000 | C29: =+B29-'Costos Fijos'!L30 -> -1619522.9 | D29: =IFERROR(1-(C29/B29),"") -> 1.7388334 | E29: =COUNTIFS(Ordenes!U:U,MONTH(A29 &17),Ordenes!AC:AC,A$17) -> 12 | F29: =COUNTIFS(Ordenes!V:V,MONTH(A29 &17),Ordenes!AD:AD,A$17) -> 11 | G29: =B29-C29 -> 3811522.9 | H29: =+C29 -> -1619522.9 | I29: =IFERROR(+H29/B29,"") -> -0.73883344 | J29: =-SUMIFS(Ordenes!W$2:W$1493,Ordenes!AF$2:AF$1493,MONTH(A29 &17),Ordenes!AE$2:AE$1493,A$17) -> 0 | K29: 3758000 | L29: 1086950.1 | M29: 1200 | O29: TOTAL REAL EN CAJA | P29: =P27+P28+L30-K30 -> 4694551.6
A30: ANUAL | B30: =SUM(B18:B29) -> 59075501 | C30: =SUM(C18:C29) -> 5933135.7 | D30: =IFERROR(1-(C30/B30),"") -> 0.8995669 | E30: =SUM(E18:E29) -> 227 | F30: =SUM(F18:F29) -> 222 | G30: =B30-C30 -> 53142365 | H30: =+C30 -> 5933135.7 | I30: =IFERROR(+H30/B30,"") -> 0.1004331 | J30: =SUM(J18:J29) -> 172500 | K30: =SUM(K18:K29) -> 15040382 | L30: =SUM(L18:L29) -> 17005848 | M30: =SUM(M18:M29)+M14 -> 11289.03 | O30: DIEFERENCIA CON CAJA BRC | P30: =P29-'[5]2025'!$P$500 -> 0
B31: =(B30/B14)-1 -> 0.67402099 | C31: =(C30/C14)-1 -> 0.66325565
A33: 2026 | B33: Facturacion | C33: Ganacia neta | D33: % costos fijos | E33: Cant Rep | F33: Cant Ent | G33: Dif GB-Fact | H33: Ganancia ELS | I33: Utilidad neta | J33: A COBRAR | K33: INVERTIDO | L33: INGRESO POR INVERSIÓN | M33: DÓLARES
A34: Enero | B34: =SUMIFS(Ordenes!R$2:R$1493,Ordenes!AF$2:AF$1493,MONTH(A34 &1),Ordenes!AE$2:AE$1493,A$33) -> 5807500 | C34: =+B34-'Costos Fijos'!L36 -> 3291552.9 | D34: =IFERROR(1-(C34/B34),"") -> 0.43322378 | E34: =COUNTIFS(Ordenes!U:U,MONTH(A34 &17),Ordenes!AC:AC,A$33) -> 14 | F34: =COUNTIFS(Ordenes!V:V,MONTH(A34 &17),Ordenes!AD:AD,A$33) -> 23 | G34: =B34-C34 -> 2515947.1 | H34: =+C34 -> 3291552.9 | I34: =IFERROR(+H34/B34,"") -> 0.56677622 | J34: =-SUMIFS(Ordenes!W$2:W$1493,Ordenes!AF$2:AF$1493,MONTH(A34 &34),Ordenes!AE$2:AE$1493,A$33) -> 0 | L34: 2000000
A35: Febrero | B35: =SUMIFS(Ordenes!R$2:R$1493,Ordenes!AF$2:AF$1493,MONTH(A35 &1),Ordenes!AE$2:AE$1493,A$33) -> 4804000 | C35: =+B35-'Costos Fijos'!L37 -> 1690880 | D35: =IFERROR(1-(C35/B35),"") -> 0.64802665 | E35: =COUNTIFS(Ordenes!U:U,MONTH(A35 &17),Ordenes!AC:AC,A$33) -> 18 | F35: =COUNTIFS(Ordenes!V:V,MONTH(A35 &17),Ordenes!AD:AD,A$33) -> 16 | G35: =B35-C35 -> 3113120 | H35: =+C35 -> 1690880 | I35: =IFERROR(+H35/B35,"") -> 0.35197335 | J35: =-SUMIFS(Ordenes!W$2:W$1493,Ordenes!AF$2:AF$1493,MONTH(A35 &34),Ordenes!AE$2:AE$1493,A$33) -> 0
A36: Marzo | B36: =SUMIFS(Ordenes!R$2:R$1493,Ordenes!AF$2:AF$1493,MONTH(A36 &1),Ordenes!AE$2:AE$1493,A$33) -> 4624500 | C36: =+B36-'Costos Fijos'!L38 -> 1404910.8 | D36: =IFERROR(1-(C36/B36),"") -> 0.69620266 | E36: =COUNTIFS(Ordenes!U:U,MONTH(A36 &17),Ordenes!AC:AC,A$33) -> 22 | F36: =COUNTIFS(Ordenes!V:V,MONTH(A36 &17),Ordenes!AD:AD,A$33) -> 18 | G36: =B36-C36 -> 3219589.2 | H36: =+C36 -> 1404910.8 | I36: =IFERROR(+H36/B36,"") -> 0.30379734 | J36: =-SUMIFS(Ordenes!W$2:W$1493,Ordenes!AF$2:AF$1493,MONTH(A36 &34),Ordenes!AE$2:AE$1493,A$33) -> 435000
A37: Abril | B37: =SUMIFS(Ordenes!R$2:R$1493,Ordenes!AF$2:AF$1493,MONTH(A37 &1),Ordenes!AE$2:AE$1493,A$33) -> 2527300 | C37: =+B37-'Costos Fijos'!L39 -> -748232.42 | D37: =IFERROR(1-(C37/B37),"") -> 1.29606 | E37: =COUNTIFS(Ordenes!U:U,MONTH(A37 &17),Ordenes!AC:AC,A$33) -> 17 | F37: =COUNTIFS(Ordenes!V:V,MONTH(A37 &17),Ordenes!AD:AD,A$33) -> 14 | G37: =B37-C37 -> 3275532.4 | H37: =+C37 -> -748232.42 | I37: =IFERROR(+H37/B37,"") -> -0.29605999 | J37: =-SUMIFS(Ordenes!W$2:W$1493,Ordenes!AF$2:AF$1493,MONTH(A37 &34),Ordenes!AE$2:AE$1493,A$33) -> 177500 | K37: 702500 | M37: 500
A38: Mayo | B38: =SUMIFS(Ordenes!R$2:R$1493,Ordenes!AF$2:AF$1493,MONTH(A38 &1),Ordenes!AE$2:AE$1493,A$33) -> 1837000 | C38: =+B38-'Costos Fijos'!L40 -> 1837000 | D38: =IFERROR(1-(C38/B38),"") -> 0 | E38: =COUNTIFS(Ordenes!U:U,MONTH(A38 &17),Ordenes!AC:AC,A$33) -> 6 | F38: =COUNTIFS(Ordenes!V:V,MONTH(A38 &17),Ordenes!AD:AD,A$33) -> 6 | G38: =B38-C38 -> 0 | H38: =+C38 -> 1837000 | I38: =IFERROR(+H38/B38,"") -> 1 | J38: =-SUMIFS(Ordenes!W$2:W$1493,Ordenes!AF$2:AF$1493,MONTH(A38 &34),Ordenes!AE$2:AE$1493,A$33) -> 1553000
A39: Junio | B39: =SUMIFS(Ordenes!R$2:R$1493,Ordenes!AF$2:AF$1493,MONTH(A39 &1),Ordenes!AE$2:AE$1493,A$33) -> 0 | C39: =+B39-'Costos Fijos'!L41 -> 0 | D39: =IFERROR(1-(C39/B39),"") | E39: =COUNTIFS(Ordenes!U:U,MONTH(A39 &17),Ordenes!AC:AC,A$33) -> 0 | F39: =COUNTIFS(Ordenes!V:V,MONTH(A39 &17),Ordenes!AD:AD,A$33) -> 0 | G39: =B39-C39 -> 0 | H39: =+C39 -> 0 | I39: =IFERROR(+H39/B39,"") | J39: =-SUMIFS(Ordenes!W$2:W$1493,Ordenes!AF$2:AF$1493,MONTH(A39 &34),Ordenes!AE$2:AE$1493,A$33) -> 0
A40: Julio | B40: =SUMIFS(Ordenes!R$2:R$1493,Ordenes!AF$2:AF$1493,MONTH(A40 &1),Ordenes!AE$2:AE$1493,A$33) -> 0 | C40: =+B40-'Costos Fijos'!L42 -> 0 | D40: =IFERROR(1-(C40/B40),"") | E40: =COUNTIFS(Ordenes!U:U,MONTH(A40 &17),Ordenes!AC:AC,A$33) -> 0 | F40: =COUNTIFS(Ordenes!V:V,MONTH(A40 &17),Ordenes!AD:AD,A$33) -> 0 | G40: =B40-C40 -> 0 | H40: =+C40 -> 0 | I40: =IFERROR(+H40/B40,"") | J40: =-SUMIFS(Ordenes!W$2:W$1493,Ordenes!AF$2:AF$1493,MONTH(A40 &34),Ordenes!AE$2:AE$1493,A$33) -> 0
A41: Agosto | B41: =SUMIFS(Ordenes!R$2:R$1493,Ordenes!AF$2:AF$1493,MONTH(A41 &1),Ordenes!AE$2:AE$1493,A$33) -> 0 | C41: =+B41-'Costos Fijos'!L43 -> 0 | D41: =IFERROR(1-(C41/B41),"") | E41: =COUNTIFS(Ordenes!U:U,MONTH(A41 &17),Ordenes!AC:AC,A$33) -> 0 | F41: =COUNTIFS(Ordenes!V:V,MONTH(A41 &17),Ordenes!AD:AD,A$33) -> 0 | G41: =B41-C41 -> 0 | H41: =+C41 -> 0 | I41: =IFERROR(+H41/B41,"") | J41: =-SUMIFS(Ordenes!W$2:W$1493,Ordenes!AF$2:AF$1493,MONTH(A41 &34),Ordenes!AE$2:AE$1493,A$33) -> 0
A42: Septiembre | B42: =SUMIFS(Ordenes!R$2:R$1493,Ordenes!AF$2:AF$1493,MONTH(A42 &1),Ordenes!AE$2:AE$1493,A$33) -> 0 | C42: =+B42-'Costos Fijos'!L44 -> 0 | D42: =IFERROR(1-(C42/B42),"") | E42: =COUNTIFS(Ordenes!U:U,MONTH(A42 &17),Ordenes!AC:AC,A$33) -> 0 | F42: =COUNTIFS(Ordenes!V:V,MONTH(A42 &17),Ordenes!AD:AD,A$33) -> 0 | G42: =B42-C42 -> 0 | H42: =+C42 -> 0 | I42: =IFERROR(+H42/B42,"") | J42: =-SUMIFS(Ordenes!W$2:W$1493,Ordenes!AF$2:AF$1493,MONTH(A42 &34),Ordenes!AE$2:AE$1493,A$33) -> 0
A43: Octubre | B43: =SUMIFS(Ordenes!R$2:R$1493,Ordenes!AF$2:AF$1493,MONTH(A43 &1),Ordenes!AE$2:AE$1493,A$33) -> 0 | C43: =+B43-'Costos Fijos'!L45 -> 0 | D43: =IFERROR(1-(C43/B43),"") | E43: =COUNTIFS(Ordenes!U:U,MONTH(A43 &17),Ordenes!AC:AC,A$33) -> 0 | F43: =COUNTIFS(Ordenes!V:V,MONTH(A43 &17),Ordenes!AD:AD,A$33) -> 0 | G43: =B43-C43 -> 0 | H43: =+C43 -> 0 | I43: =IFERROR(+H43/B43,"") | J43: =-SUMIFS(Ordenes!W$2:W$1493,Ordenes!AF$2:AF$1493,MONTH(A43 &34),Ordenes!AE$2:AE$1493,A$33) -> 0 | P43: =P29+H46-J46 -> 10005163
A44: Noviembre | B44: =SUMIFS(Ordenes!R$2:R$1493,Ordenes!AF$2:AF$1493,MONTH(A44 &1),Ordenes!AE$2:AE$1493,A$33) -> 0 | C44: =+B44-'Costos Fijos'!L46 -> 0 | D44: =IFERROR(1-(C44/B44),"") | E44: =COUNTIFS(Ordenes!U:U,MONTH(A44 &17),Ordenes!AC:AC,A$33) -> 0 | F44: =COUNTIFS(Ordenes!V:V,MONTH(A44 &17),Ordenes!AD:AD,A$33) -> 0 | G44: =B44-C44 -> 0 | H44: =+C44 -> 0 | I44: =IFERROR(+H44/B44,"") | J44: =-SUMIFS(Ordenes!W$2:W$1493,Ordenes!AF$2:AF$1493,MONTH(A44 &34),Ordenes!AE$2:AE$1493,A$33) -> 0 | O44: EQUIPOS 2024 COBRADOS EN 2025
A45: Diciembre | B45: =SUMIFS(Ordenes!R$2:R$1493,Ordenes!AF$2:AF$1493,MONTH(A45 &1),Ordenes!AE$2:AE$1493,A$33) -> 0 | C45: =+B45-'Costos Fijos'!L47 -> 0 | D45: =IFERROR(1-(C45/B45),"") | E45: =COUNTIFS(Ordenes!U:U,MONTH(A45 &17),Ordenes!AC:AC,A$33) -> 0 | F45: =COUNTIFS(Ordenes!V:V,MONTH(A45 &17),Ordenes!AD:AD,A$33) -> 0 | G45: =B45-C45 -> 0 | H45: =+C45 -> 0 | I45: =IFERROR(+H45/B45,"") | J45: =-SUMIFS(Ordenes!W$2:W$1493,Ordenes!AF$2:AF$1493,MONTH(A45 &34),Ordenes!AE$2:AE$1493,A$33) -> 0 | O45: TOTAL REAL EN CAJA | P45: =P43+P44+L46-K46 -> 11302663
A46: ANUAL | B46: =SUM(B34:B45) -> 19600300 | C46: =SUM(C34:C45) -> 7476111.3 | D46: =IFERROR(1-(C46/B46),"") -> 0.61857159 | E46: =SUM(E34:E45) -> 77 | F46: =SUM(F34:F45) -> 77 | G46: =B46-C46 -> 12124189 | H46: =+C46 -> 7476111.3 | I46: =IFERROR(+H46/B46,"") -> 0.38142841 | J46: =SUM(J34:J45) -> 2165500 | K46: =SUM(K34:K45) -> 702500 | L46: =SUM(L34:L45) -> 2000000 | M46: =SUM(M34:M45)+M30 -> 11789.03 | O46: DIEFERENCIA CON CAJA BRC | P46: =P45-'[5]2026'!$M$500 -> 3932800
B47: =(B46/B30)-1 -> -0.6682161 | C47: =(C46/C30)-1 -> 0.26006074
